Workbook
Name UPDATE: 'Data Sheet'!$E$1

Sheet HISTORICAL FS
B1: ="HISTORICAL FINANCIAL STATEMENT-"&'Data Sheet'!B1 -> HISTORICAL FINANCIAL STATEMENT-RELIANCE INDUSTRIES LTD
B2: YEAR | C2: ='Data Sheet'!B16 -> 42460 | D2: ='Data Sheet'!C16 -> 42825 | E2: ='Data Sheet'!D16 -> 43190 | F2: ='Data Sheet'!E16 -> 43555 | G2: ='Data Sheet'!F16 -> 43921 | H2: ='Data Sheet'!G16 -> 44286 | I2: ='Data Sheet'!H16 -> 44651 | J2: ='Data Sheet'!I16 -> 45016 | ... L2: ='Data Sheet'!K16 -> 45747 | M2: LTM
B3: INCOME STATEMENT
B4: Salas | C4: =IFERROR('Data Sheet'!B17,0) -> 272583 | D4: =IFERROR('Data Sheet'!C17,0) -> 303954 | E4: =IFERROR('Data Sheet'!D17,0) -> 390823 | F4: =IFERROR('Data Sheet'!E17,0) -> 568337 | G4: =IFERROR('Data Sheet'!F17,0) -> 596679 | H4: =IFERROR('Data Sheet'!G17,0) -> 466307 | I4: =IFERROR('Data Sheet'!H17,0) -> 694673 | J4: =IFERROR('Data Sheet'!I17,0) -> 876396 | ... L4: =IFERROR('Data Sheet'!K17,0) -> 962820 | M4: =IFERROR(SUM('Data Sheet'!H17:K17),0) -> 3432930
B5: salas Growth | C5: - | D5: =D4/C4-1 -> 0.11508788 | E5: =E4/D4-1 -> 0.28579654 | F5: =F4/E4-1 -> 0.45420561 | G5: =G4/F4-1 -> 0.0498683 | H5: =H4/G4-1 -> -0.21849604 | I5: =I4/H4-1 -> 0.48973316 | J5: =J4/I4-1 -> 0.26159502 | K5: =K4/J4-1 -> 0.025838776 | ... M5: =M4/L4-1 -> 2.5654951
B7: COGS | C7: =IFERROR(SUM('Data Sheet'!B18,'Data Sheet'!B20,'Data Sheet'!B21,'Data Sheet'!B22,)-1*'Data Sheet'!B19,0) -> 215234 | D7: =IFERROR(SUM('Data Sheet'!C18,'Data Sheet'!C20,'Data Sheet'!C21,'Data Sheet'!C22,)-1*'Data Sheet'!C19,0) -> 241848 | E7: =IFERROR(SUM('Data Sheet'!D18,'Data Sheet'!D20,'Data Sheet'!D21,'Data Sheet'!D22,)-1*'Data Sheet'!D19,0) -> 301249 | F7: =IFERROR(SUM('Data Sheet'!E18,'Data Sheet'!E20,'Data Sheet'!E21,'Data Sheet'!E22,)-1*'Data Sheet'!E19,0) -> 436202 | G7: =IFERROR(SUM('Data Sheet'!F18,'Data Sheet'!F20,'Data Sheet'!F21,'Data Sheet'!F22,)-1*'Data Sheet'!F19,0) -> 445847 | H7: =IFERROR(SUM('Data Sheet'!G18,'Data Sheet'!G20,'Data Sheet'!G21,'Data Sheet'!G22,)-1*'Data Sheet'!G19,0) -> 328419 | I7: =IFERROR(SUM('Data Sheet'!H18,'Data Sheet'!H20,'Data Sheet'!H21,'Data Sheet'!H22,)-1*'Data Sheet'!H19,0) -> 521826 | J7: =IFERROR(SUM('Data Sheet'!I18,'Data Sheet'!I20,'Data Sheet'!I21,'Data Sheet'!I22,)-1*'Data Sheet'!I19,0) -> 658075 | ... L7: =IFERROR(SUM('Data Sheet'!K18,'Data Sheet'!K20,'Data Sheet'!K21,'Data Sheet'!K22,)-1*'Data Sheet'!K19,0) -> 700429 | M7: =IFERROR(SUM('Data Sheet'!H42:K42),0) -> 999629
B8: COGS % Salas | C8: =C7/C4 -> 0.78960904 | D8: =D7/D4 -> 0.79567303 | E8: =E7/E4 -> 0.77080673 | F8: =F7/F4 -> 0.7675059 | G8: =G7/G4 -> 0.74721416 | H8: =H7/H4 -> 0.70429781 | I8: =I7/I4 -> 0.75118221 | J8: =J7/J4 -> 0.75088773 | ... M8: =M7/M4 -> 0.29118829
B10: GROSS PROFIT | C10: =C4-C7 -> 57349 | D10: =D4-D7 -> 62106 | E10: =E4-E7 -> 89574 | F10: =F4-F7 -> 132135 | G10: =G4-G7 -> 150832 | H10: =H4-H7 -> 137888 | I10: =I4-I7 -> 172847 | J10: =J4-J7 -> 218321 | ... M10: =M4-M7 -> 2433301
B11: Gross Margin | C11: =C10/C4 -> 0.21039096 | D11: =D10/D4 -> 0.20432697 | E11: =E10/E4 -> 0.22919327 | F11: =F10/F4 -> 0.2324941 | G11: =G10/G4 -> 0.25278584 | H11: =H10/H4 -> 0.29570219 | I11: =I10/I4 -> 0.24881779 | J11: =J10/J4 -> 0.24911227 | ... M11: =M10/M4 -> 0.70881171
B13: SELLING & GENEREAL EXP | C13: =IFERROR(SUM('Data Sheet'!B23,'Data Sheet'!B24),0) -> 15568 | D13: =IFERROR(SUM('Data Sheet'!C23,'Data Sheet'!C24),0) -> 15799 | E13: =IFERROR(SUM('Data Sheet'!D23,'Data Sheet'!D24),0) -> 25259 | F13: =IFERROR(SUM('Data Sheet'!E23,'Data Sheet'!E24),0) -> 47885 | G13: =IFERROR(SUM('Data Sheet'!F23,'Data Sheet'!F24),0) -> 61566 | H13: =IFERROR(SUM('Data Sheet'!G23,'Data Sheet'!G24),0) -> 57098 | I13: =IFERROR(SUM('Data Sheet'!H23,'Data Sheet'!H24),0) -> 64266 | J13: =IFERROR(SUM('Data Sheet'!I23,'Data Sheet'!I24),0) -> 76003 | ... M13: =IFERROR(SUM('Data Sheet'!L23,'Data Sheet'!L24),0) -> 0
B14: S&A Exp % Salas | C14: =C13/C4 -> 0.057112879 | D14: =D13/D4 -> 0.05197826 | E14: =E13/E4 -> 0.06463028 | F14: =F13/F4 -> 0.084254588 | G14: =G13/G4 -> 0.10318111 | H14: =H13/H4 -> 0.12244723 | I14: =I13/I4 -> 0.092512592 | J14: =J13/J4 -> 0.086722212 | ... M14: =M13/M4 -> 0
B16: EBIDA | C16: =C10-C13 -> 41781 | D16: =D10-D13 -> 46307 | E16: =E10-E13 -> 64315 | F16: =F10-F13 -> 84250 | G16: =G10-G13 -> 89266 | H16: =H10-H13 -> 80790 | I16: =I10-I13 -> 108581 | J16: =J10-J13 -> 142318 | ... M16: =M10-M13 -> 2433301
B17: EBIDA % Salas | C17: =C16/C4 -> 0.15327808 | D17: =D16/D4 -> 0.15234871 | E17: =E16/E4 -> 0.16456299 | F17: =F16/F4 -> 0.14823951 | G17: =G16/G4 -> 0.14960473 | H17: =H16/H4 -> 0.17325496 | I17: =I16/I4 -> 0.1563052 | J17: =J16/J4 -> 0.16239006 | ... M17: =M16/M4 -> 0.70881171
B19: INTEREST | C19: =IFERROR('Data Sheet'!B27,0) -> 3691 | D19: =IFERROR('Data Sheet'!C27,0) -> 3849 | E19: =IFERROR('Data Sheet'!D27,0) -> 8052 | F19: =IFERROR('Data Sheet'!E27,0) -> 16495 | G19: =IFERROR('Data Sheet'!F27,0) -> 22027 | H19: =IFERROR('Data Sheet'!G27,0) -> 21189 | I19: =IFERROR('Data Sheet'!H27,0) -> 14584 | J19: =IFERROR('Data Sheet'!I27,0) -> 19571 | ... L19: =IFERROR('Data Sheet'!K27,0) -> 24269 | M19: =IFERROR(SUM('Data Sheet'!H27:K27),0) -> 81542
B20: Interest % Salas | C20: =C19/C4 -> 0.01354083 | D20: =D19/D4 -> 0.0126631 | E20: =E19/E4 -> 0.020602677 | F20: =F19/F4 -> 0.029023273 | G20: =G19/G4 -> 0.036915997 | H20: =H19/H4 -> 0.045440021 | I20: =I19/I4 -> 0.02099405 | J20: =J19/J4 -> 0.022331229 | ... M20: =M19/M4 -> 0.023752887
B22: Depreciation | C22: =IFERROR('Data Sheet'!B26,0) -> 11565 | D22: =IFERROR('Data Sheet'!C26,0) -> 11646 | E22: =IFERROR('Data Sheet'!D26,0) -> 16706 | F22: =IFERROR('Data Sheet'!E26,0) -> 20934 | G22: =IFERROR('Data Sheet'!F26,0) -> 22203 | H22: =IFERROR('Data Sheet'!G26,0) -> 26572 | I22: =IFERROR('Data Sheet'!H26,0) -> 29782 | J22: =IFERROR('Data Sheet'!I26,0) -> 40303 | ... L22: =IFERROR('Data Sheet'!K26,0) -> 53136 | M22: =IFERROR(SUM('Data Sheet'!H26:K26),0) -> 174053
B23: Depreciation % Salas | C23: =C22/C4 -> 0.042427444 | D23: =D22/D4 -> 0.038315008 | E23: =E22/E4 -> 0.042745693 | F23: =F22/F4 -> 0.03683378 | G23: =G22/G4 -> 0.037210963 | H23: =H22/H4 -> 0.056983918 | I23: =I22/I4 -> 0.04287197 | J23: =J22/J4 -> 0.045987202 | ... M23: =M22/M4 -> 0.050701005
B25: Earning Before Taxes | C25: =IFERROR(C16-SUM(C19,C22),0) -> 26525 | D25: =IFERROR(D16-SUM(D19,D22),0) -> 30812 | E25: =IFERROR(E16-SUM(E19,E22),0) -> 39557 | F25: =IFERROR(F16-SUM(F19,F22),0) -> 46821 | G25: =IFERROR(G16-SUM(G19,G22),0) -> 45036 | H25: =IFERROR(H16-SUM(H19,H22),0) -> 33029 | I25: =IFERROR(I16-SUM(I19,I22),0) -> 64215 | J25: =IFERROR(J16-SUM(J19,J22),0) -> 82444 | ... M25: =IFERROR(M16-SUM(M19,M22),0) -> 2177706
B26: EBT % Salas | C26: =C25/C4 -> 0.09730981 | D26: =D25/D4 -> 0.1013706 | E26: =E25/E4 -> 0.10121462 | F26: =F25/F4 -> 0.08238246 | G26: =G25/G4 -> 0.075477769 | H26: =H25/H4 -> 0.070831019 | I26: =I25/I4 -> 0.092439176 | J26: =J25/J4 -> 0.09407163 | ... M26: =M25/M4 -> 0.63435782
B28: TAX | C28: =IFERROR('Data Sheet'!B29,0) -> 8876 | D28: =IFERROR('Data Sheet'!C29,0) -> 10201 | E28: =IFERROR('Data Sheet'!D29,0) -> 13346 | F28: =IFERROR('Data Sheet'!E29,0) -> 15390 | G28: =IFERROR('Data Sheet'!F29,0) -> 13726 | H28: =IFERROR('Data Sheet'!G29,0) -> 1722 | I28: =IFERROR('Data Sheet'!H29,0) -> 15970 | J28: =IFERROR('Data Sheet'!I29,0) -> 20376 | ... L28: =IFERROR('Data Sheet'!K29,0) -> 25230 | M28: =IFERROR(SUM('Data Sheet'!H28:K28),0) -> 388636
B29: Effectiv tax Rate | C29: =C28/C25 -> 0.33462771 | D29: =D28/D25 -> 0.33107231 | E29: =E28/E25 -> 0.33738656 | F29: =F28/F25 -> 0.32869866 | G29: =G28/G25 -> 0.3047784 | H29: =H28/H25 -> 0.052136002 | I29: =I28/I25 -> 0.24869579 | J29: =J28/J25 -> 0.24714958 | ... M29: =M28/M25 -> 0.17846119
B31: Net Profit | C31: =C25-C28 -> 17649 | D31: =D25-D28 -> 20611 | E31: =E25-E28 -> 26211 | F31: =F25-F28 -> 31431 | G31: =G25-G28 -> 31310 | H31: =H25-H28 -> 31307 | I31: =I25-I28 -> 48245 | J31: =J25-J28 -> 62068 | ... M31: =M25-M28 -> 1789070
B32: Net Margin | C32: =C31/C4 -> 0.064747251 | D32: =D31/D4 -> 0.067809603 | E32: =E31/E4 -> 0.067066166 | F32: =F31/F4 -> 0.055303456 | G32: =G31/G4 -> 0.052473776 | H32: =H31/H4 -> 0.067138173 | I32: =I31/I4 -> 0.069449943 | J32: =J31/J4 -> 0.070821866 | ... M32: =M31/M4 -> 0.52114957
B34: No.of Equity Shares | C34: =IFERROR('Data Sheet'!B93,0) -> 1382.58 | D34: =IFERROR('Data Sheet'!C93,0) -> 1387.22 | E34: =IFERROR('Data Sheet'!D93,0) -> 1351.39 | F34: =IFERROR('Data Sheet'!E93,0) -> 1352.26 | G34: =IFERROR('Data Sheet'!F93,0) -> 1352.37 | H34: =IFERROR('Data Sheet'!G93,0) -> 1267.89 | I34: =IFERROR('Data Sheet'!H93,0) -> 1352.98 | J34: =IFERROR('Data Sheet'!I93,0) -> 1353.12 | ... M34: =IFERROR('Data Sheet'!L93,0) -> 0
B36: EPS | C36: =IFERROR(C31/C34,0) -> 12.765265 | D36: =IFERROR(D31/D34,0) -> 14.857773 | E36: =IFERROR(E31/E34,0) -> 19.395585 | F36: =IFERROR(F31/F34,0) -> 23.243311 | G36: =IFERROR(G31/G34,0) -> 23.151948 | H36: =IFERROR(H31/H34,0) -> 24.692205 | I36: =IFERROR(I31/I34,0) -> 35.658325 | J36: =IFERROR(J31/J34,0) -> 45.870285 | ... M36: =IFERROR(M31/M34,0) -> 0
B37: EPS Growth % | D37: =D36/C36-1 -> 0.16392203 | E37: =E36/D36-1 -> 0.30541671 | F37: =F36/E36-1 -> 0.19838153 | G37: =G36/F36-1 -> -0.0039307281 | H37: =H36/G36-1 -> 0.066528186 | I37: =I36/H36-1 -> 0.4441126 | J37: =J36/I36-1 -> 0.28638363 | K37: =K36/J36-1 -> 0.012439118 | ... M37: =M36/L36-1 -> -1
B39: Dividend Per Shares | C39: =IFERROR('Data Sheet'!B31/'HISTORICAL FS'!C34,0) -> 2.2388578 | D39: =IFERROR('Data Sheet'!C31/'HISTORICAL FS'!D34,0) -> 2.3463474 | E39: =IFERROR('Data Sheet'!D31/'HISTORICAL FS'!E34,0) -> 2.6292928 | F39: =IFERROR('Data Sheet'!E31/'HISTORICAL FS'!F34,0) -> 2.8484907 | G39: =IFERROR('Data Sheet'!F31/'HISTORICAL FS'!G34,0) -> 3.0467624 | H39: =IFERROR('Data Sheet'!G31/'HISTORICAL FS'!H34,0) -> 3.558274 | I39: =IFERROR('Data Sheet'!H31/'HISTORICAL FS'!I34,0) -> 4.0000591 | J39: =IFERROR('Data Sheet'!I31/'HISTORICAL FS'!J34,0) -> 4.5002661 | ... M39: =IFERROR('Data Sheet'!L31/'HISTORICAL FS'!M34,0) -> 0
B41: Dividend Pay Out Ratio | C41: =IFERROR(C39/C36,0) -> 0.17538671 | D41: =IFERROR(D39/D36,0) -> 0.15792053 | E41: =IFERROR(E39/E36,0) -> 0.13556141 | F41: =IFERROR(F39/F36,0) -> 0.12255098 | G41: =IFERROR(G39/G36,0) -> 0.13159853 | H41: =IFERROR(H39/H36,0) -> 0.14410515 | I41: =IFERROR(I39/I36,0) -> 0.11217743 | J41: =IFERROR(J39/J36,0) -> 0.098108526 | ... M41: =IFERROR(M39/M36,0) -> 0
B43: Retained Earnings | C43: =IFERROR(1-C41,0) -> 0.82461329 | D43: =IFERROR(1-D41,0) -> 0.84207947 | E43: =IFERROR(1-E41,0) -> 0.86443859 | F43: =IFERROR(1-F41,0) -> 0.87744902 | G43: =IFERROR(1-G41,0) -> 0.86840147 | H43: =IFERROR(1-H41,0) -> 0.85589485 | I43: =IFERROR(1-I41,0) -> 0.88782257 | J43: =IFERROR(1-J41,0) -> 0.90189147 | ... M43: =IFERROR(1-M41,0) -> 1
A46: # | B46: Balance Sheet
B47: ='Balance Sheet'!A4 -> Equity Share Capital | C47: =IFERROR( 'Balance Sheet'!B4,0) -> 2948 | D47: =IFERROR( 'Balance Sheet'!C4,0) -> 2959 | E47: =IFERROR( 'Balance Sheet'!D4,0) -> 5922 | F47: =IFERROR( 'Balance Sheet'!E4,0) -> 5926 | G47: =IFERROR( 'Balance Sheet'!F4,0) -> 6339 | H47: =IFERROR( 'Balance Sheet'!G4,0) -> 6445 | I47: =IFERROR( 'Balance Sheet'!H4,0) -> 6765 | J47: =IFERROR( 'Balance Sheet'!I4,0) -> 6766 | ... M47: =IFERROR( 'Balance Sheet'!L4,0) -> 0
B48: ='Balance Sheet'!A5 -> Reserves | C48: =IFERROR( 'Balance Sheet'!B5,0) -> 228608 | D48: =IFERROR( 'Balance Sheet'!C5,0) -> 260750 | E48: =IFERROR( 'Balance Sheet'!D5,0) -> 287584 | F48: =IFERROR( 'Balance Sheet'!E5,0) -> 381186 | G48: =IFERROR( 'Balance Sheet'!F5,0) -> 442827 | H48: =IFERROR( 'Balance Sheet'!G5,0) -> 693727 | I48: =IFERROR( 'Balance Sheet'!H5,0) -> 772720 | J48: =IFERROR( 'Balance Sheet'!I5,0) -> 709106 | ... M48: =IFERROR( 'Balance Sheet'!L5,0) -> 0
B49: ='Balance Sheet'!A6 -> Borrowings | C49: =IFERROR( 'Balance Sheet'!B6,0) -> 194714 | D49: =IFERROR( 'Balance Sheet'!C6,0) -> 217475 | E49: =IFERROR( 'Balance Sheet'!D6,0) -> 239843 | F49: =IFERROR( 'Balance Sheet'!E6,0) -> 307714 | G49: =IFERROR( 'Balance Sheet'!F6,0) -> 355133 | H49: =IFERROR( 'Balance Sheet'!G6,0) -> 278962 | I49: =IFERROR( 'Balance Sheet'!H6,0) -> 319158 | J49: =IFERROR( 'Balance Sheet'!I6,0) -> 451664 | ... M49: =IFERROR( 'Balance Sheet'!L6,0) -> 0
B50: ='Balance Sheet'!A7 -> Other Liabilities | C50: =IFERROR( 'Balance Sheet'!B7,0) -> 172727 | D50: =IFERROR( 'Balance Sheet'!C7,0) -> 225618 | E50: =IFERROR( 'Balance Sheet'!D7,0) -> 277924 | F50: =IFERROR( 'Balance Sheet'!E7,0) -> 302804 | G50: =IFERROR( 'Balance Sheet'!F7,0) -> 358716 | H50: =IFERROR( 'Balance Sheet'!G7,0) -> 340931 | I50: =IFERROR( 'Balance Sheet'!H7,0) -> 399979 | J50: =IFERROR( 'Balance Sheet'!I7,0) -> 438346 | ... M50: =IFERROR( 'Balance Sheet'!L7,0) -> 0
B51: Total Liabilities | C51: =IFERROR( 'Balance Sheet'!B8,0) -> 598997 | D51: =IFERROR( 'Balance Sheet'!C8,0) -> 706802 | E51: =IFERROR( 'Balance Sheet'!D8,0) -> 811273 | F51: =IFERROR( 'Balance Sheet'!E8,0) -> 997630 | G51: =IFERROR( 'Balance Sheet'!F8,0) -> 1163015 | H51: =IFERROR( 'Balance Sheet'!G8,0) -> 1320065 | I51: =IFERROR( 'Balance Sheet'!H8,0) -> 1498622 | J51: =IFERROR( 'Balance Sheet'!I8,0) -> 1605882 | ... M51: =IFERROR( 'Balance Sheet'!L8,0) -> 0
B53: Fixed Asset Net Block | C53: =IFERROR('Balance Sheet'!B10,0) -> 184910 | D53: =IFERROR('Balance Sheet'!C10,0) -> 198526 | E53: =IFERROR('Balance Sheet'!D10,0) -> 403885 | F53: =IFERROR('Balance Sheet'!E10,0) -> 398374 | G53: =IFERROR('Balance Sheet'!F10,0) -> 532658 | H53: =IFERROR('Balance Sheet'!G10,0) -> 541258 | I53: =IFERROR('Balance Sheet'!H10,0) -> 627798 | J53: =IFERROR('Balance Sheet'!I10,0) -> 724805 | ... M53: =IFERROR('Balance Sheet'!L10,0) -> 0
B54: ='Balance Sheet'!A11 -> Capital Work in Progress | C54: =IFERROR('Balance Sheet'!B11,0) -> 228697 | D54: =IFERROR('Balance Sheet'!C11,0) -> 324837 | E54: =IFERROR('Balance Sheet'!D11,0) -> 187022 | F54: =IFERROR('Balance Sheet'!E11,0) -> 179463 | G54: =IFERROR('Balance Sheet'!F11,0) -> 109106 | H54: =IFERROR('Balance Sheet'!G11,0) -> 125953 | I54: =IFERROR('Balance Sheet'!H11,0) -> 172506 | J54: =IFERROR('Balance Sheet'!I11,0) -> 293752 | ... M54: =IFERROR('Balance Sheet'!L11,0) -> 0
B55: ='Balance Sheet'!A12 -> Investments | C55: =IFERROR('Balance Sheet'!B12,0) -> 84015 | D55: =IFERROR('Balance Sheet'!C12,0) -> 82899 | E55: =IFERROR('Balance Sheet'!D12,0) -> 82862 | F55: =IFERROR('Balance Sheet'!E12,0) -> 235635 | G55: =IFERROR('Balance Sheet'!F12,0) -> 276767 | H55: =IFERROR('Balance Sheet'!G12,0) -> 364828 | I55: =IFERROR('Balance Sheet'!H12,0) -> 394264 | J55: =IFERROR('Balance Sheet'!I12,0) -> 235560 | ... M55: =IFERROR('Balance Sheet'!L12,0) -> 0
B56: ='Balance Sheet'!A13 -> Other Assets | C56: =IFERROR('Balance Sheet'!B13-SUM('Data Sheet'!B67:B69),0) -> 39396 | D56: =IFERROR('Balance Sheet'!C13-SUM('Data Sheet'!C67:C69),0) -> 40389 | E56: =IFERROR('Balance Sheet'!D13-SUM('Data Sheet'!D67:D69),0) -> 54857 | F56: =IFERROR('Balance Sheet'!E13-SUM('Data Sheet'!E67:E69),0) -> 75427 | G56: =IFERROR('Balance Sheet'!F13-SUM('Data Sheet'!F67:F69),0) -> 120005 | H56: =IFERROR('Balance Sheet'!G13-SUM('Data Sheet'!G67:G69),0) -> 169943 | I56: =IFERROR('Balance Sheet'!H13-SUM('Data Sheet'!H67:H69),0) -> 136458 | J56: =IFERROR('Balance Sheet'!I13-SUM('Data Sheet'!I67:I69),0) -> 114645 | ... L56: =IFERROR('Balance Sheet'!K13-SUM('Data Sheet'!K67:K69),0) -> 150896 | M56: =IFERROR('Balance Sheet'!L13,0) -> 0
B57: Total Non Current Assets | C57: =SUM(C53:C56) -> 537018 | D57: =SUM(D53:D56) -> 646651 | E57: =SUM(E53:E56) -> 728626 | F57: =SUM(F53:F56) -> 888899 | G57: =SUM(G53:G56) -> 1038536 | H57: =SUM(H53:H56) -> 1201982 | I57: =SUM(I53:I56) -> 1331026 | J57: =SUM(J53:J56) -> 1368762 | ... L57: =SUM(L53:L56) -> 1655028 | M57: =IFERROR('Balance Sheet'!L14,0) -> 0
M58: =IFERROR('Balance Sheet'!L15,0) -> 0
B59: Receivables | C59: =IFERROR('Data Sheet'!B67,0) -> 4465 | D59: =IFERROR('Data Sheet'!C67,0) -> 8177 | E59: =IFERROR('Data Sheet'!D67,0) -> 17555 | F59: =IFERROR('Data Sheet'!E67,0) -> 30089 | G59: =IFERROR('Data Sheet'!F67,0) -> 19656 | H59: =IFERROR('Data Sheet'!G67,0) -> 19014 | I59: =IFERROR('Data Sheet'!H67,0) -> 23640 | J59: =IFERROR('Data Sheet'!I67,0) -> 28448 | ... L59: =IFERROR('Data Sheet'!K67,0) -> 42121 | M59: =IFERROR('Balance Sheet'!L16,0) -> 0
B60: ='Balance Sheet'!A18 -> Inventory | C60: =IFERROR('Data Sheet'!B68,0) -> 46486 | D60: =IFERROR('Data Sheet'!C68,0) -> 48951 | E60: =IFERROR('Data Sheet'!D68,0) -> 60837 | F60: =IFERROR('Data Sheet'!E68,0) -> 67561 | G60: =IFERROR('Data Sheet'!F68,0) -> 73903 | H60: =IFERROR('Data Sheet'!G68,0) -> 81672 | I60: =IFERROR('Data Sheet'!H68,0) -> 107778 | J60: =IFERROR('Data Sheet'!I68,0) -> 140008 | ... L60: =IFERROR('Data Sheet'!K68,0) -> 146062 | M60: =IFERROR('Balance Sheet'!L17,0) -> 0
B61: Cash and Bank | C61: =IFERROR('Data Sheet'!B69,0) -> 11028 | D61: =IFERROR('Data Sheet'!C69,0) -> 3023 | E61: =IFERROR('Data Sheet'!D69,0) -> 4255 | F61: =IFERROR('Data Sheet'!E69,0) -> 11081 | G61: =IFERROR('Data Sheet'!F69,0) -> 30920 | H61: =IFERROR('Data Sheet'!G69,0) -> 17397 | I61: =IFERROR('Data Sheet'!H69,0) -> 36178 | J61: =IFERROR('Data Sheet'!I69,0) -> 68664 | ... L61: =IFERROR('Data Sheet'!K69,0) -> 106502 | M61: =IFERROR('Balance Sheet'!L18,0) -> 0
B62: Total Current Assets | C62: =SUM(C59:C61) -> 61979 | D62: =SUM(D59:D61) -> 60151 | E62: =SUM(E59:E61) -> 82647 | F62: =SUM(F59:F61) -> 108731 | G62: =SUM(G59:G61) -> 124479 | H62: =SUM(H59:H61) -> 118083 | I62: =SUM(I59:I61) -> 167596 | J62: =SUM(J59:J61) -> 237120 | ... L62: =SUM(L59:L61) -> 294685 | M62: =IFERROR('Balance Sheet'!L19,0) -> 0
M63: =IFERROR('Balance Sheet'!L20,0) -> 0
B64: Total Assets | C64: =SUM(C62,C57) -> 598997 | D64: =SUM(D62,D57) -> 706802 | E64: =SUM(E62,E57) -> 811273 | F64: =SUM(F62,F57) -> 997630 | G64: =SUM(G62,G57) -> 1163015 | H64: =SUM(H62,H57) -> 1320065 | I64: =SUM(I62,I57) -> 1498622 | J64: =SUM(J62,J57) -> 1605882 | ... L64: =SUM(L62,L57) -> 1949713 | M64: =IFERROR('Balance Sheet'!L21,0) -> 0
B66: CHECK | C66: =C64=C51 -> TRUE | D66: =D64=D51 -> TRUE | E66: =E64=E51 -> TRUE | F66: =F64=F51 -> TRUE | G66: =G64=G51 -> TRUE | H66: =H64=H51 -> TRUE | I66: =I64=I51 -> TRUE | J66: =J64=J51 -> TRUE | ... M66: =M64=M51 -> TRUE
A68: # | B68: CASH FLOW STATEMENT
B69: Operating Activity
B70: Profit from operations | C70: =IFERROR(CFS!E5,0) -> 38887 | D70: =IFERROR(CFS!F5,0) -> 44170 | E70: =IFERROR(CFS!G5,0) -> 62765 | F70: =IFERROR(CFS!H5,0) -> 83319 | G70: =IFERROR(CFS!I5,0) -> 85347 | H70: =IFERROR(CFS!J5,0) -> 80129 | I70: =IFERROR(CFS!K5,0) -> 113726 | J70: =IFERROR(CFS!L5,0) -> 140963 | ... M70: =IFERROR(CFS!O5,0) -> 0
B71: Receivables | C71: =IFERROR(CFS!E6,0) -> -6880 | D71: =IFERROR(CFS!F6,0) -> -8511 | E71: =IFERROR(CFS!G6,0) -> -21991 | F71: =IFERROR(CFS!H6,0) -> -40136 | G71: =IFERROR(CFS!I6,0) -> -13792 | H71: =IFERROR(CFS!J6,0) -> 959 | I71: =IFERROR(CFS!K6,0) -> -14180 | J71: =IFERROR(CFS!L6,0) -> 13194 | ... M71: =IFERROR(CFS!O6,0) -> 0
B72: Inventory | C72: =IFERROR(CFS!E7,0) -> 6758 | D72: =IFERROR(CFS!F7,0) -> -6899 | E72: =IFERROR(CFS!G7,0) -> -10474 | F72: =IFERROR(CFS!H7,0) -> -6724 | G72: =IFERROR(CFS!I7,0) -> -6342 | H72: =IFERROR(CFS!J7,0) -> -7769 | I72: =IFERROR(CFS!K7,0) -> -24983 | J72: =IFERROR(CFS!L7,0) -> -32228 | ... M72: =IFERROR(CFS!O7,0) -> 0
B73: Payables | C73: =IFERROR(CFS!E8,0) -> 7951 | D73: =IFERROR(CFS!F8,0) -> 30873 | E73: =IFERROR(CFS!G8,0) -> 51003 | F73: =IFERROR(CFS!H8,0) -> 18078 | G73: =IFERROR(CFS!I8,0) -> 38050 | H73: =IFERROR(CFS!J8,0) -> -43148 | I73: =IFERROR(CFS!K8,0) -> 39888 | J73: =IFERROR(CFS!L8,0) -> -600 | ... M73: =IFERROR(CFS!O8,0) -> 0
B74: Working capital changes | C74: =IFERROR(CFS!E9,0) -> 7829 | D74: =IFERROR(CFS!F9,0) -> 15463 | E74: =IFERROR(CFS!G9,0) -> 18538 | F74: =IFERROR(CFS!H9,0) -> -28782 | G74: =IFERROR(CFS!I9,0) -> 17916 | H74: =IFERROR(CFS!J9,0) -> -49958 | I74: =IFERROR(CFS!K9,0) -> 725 | J74: =IFERROR(CFS!L9,0) -> -19634 | ... M74: =IFERROR(CFS!O9,0) -> 0
B75: Direct taxes | C75: =IFERROR(CFS!E10,0) -> -8582 | D75: =IFERROR(CFS!F10,0) -> -10083 | E75: =IFERROR(CFS!G10,0) -> -9844 | F75: =IFERROR(CFS!H10,0) -> -12191 | G75: =IFERROR(CFS!I10,0) -> -8386 | H75: =IFERROR(CFS!J10,0) -> -3213 | I75: =IFERROR(CFS!K10,0) -> -3797 | J75: =IFERROR(CFS!L10,0) -> -6297 | ... M75: =IFERROR(CFS!O10,0) -> 0
B76: other opration item | C76: - | D76: - | E76: - | F76: - | G76: - | H76: - | I76: - | J76: - | K76: - | L76: - | M76: =IFERROR(CFS!O11,0) -> 0
B77: Cash from Operating Activity | C77: =SUM(C70:C76) -> 45963 | D77: =SUM(D70:D76) -> 65013 | E77: =SUM(E70:E76) -> 89997 | F77: =SUM(F70:F76) -> 13564 | G77: =SUM(G70:G76) -> 112793 | H77: =SUM(H70:H76) -> -23000 | I77: =SUM(I70:I76) -> 111379 | J77: =SUM(J70:J76) -> 95398 | ... M77: =SUM(M70:M76) -> 0
B79: Investing Activity
B80: Fixed assets purchased | C80: =IFERROR(CFS!E12,0) -> -46898 | D80: =IFERROR(CFS!F12,0) -> -78109 | E80: =IFERROR(CFS!G12,0) -> -73953 | F80: =IFERROR(CFS!H12,0) -> -93626 | G80: =IFERROR(CFS!I12,0) -> -76517 | H80: =IFERROR(CFS!J12,0) -> -105837 | I80: =IFERROR(CFS!K12,0) -> -100145 | J80: =IFERROR(CFS!L12,0) -> -140988 | ... M80: =IFERROR(CFS!O12,0) -> 0
B81: Fixed assets sold | C81: =IFERROR(CFS!E13,0) -> 344 | D81: =IFERROR(CFS!F13,0) -> 1482 | E81: =IFERROR(CFS!G13,0) -> 999 | F81: =IFERROR(CFS!H13,0) -> 849 | G81: =IFERROR(CFS!I13,0) -> 964 | H81: =IFERROR(CFS!J13,0) -> 2319 | I81: =IFERROR(CFS!K13,0) -> 3137 | J81: =IFERROR(CFS!L13,0) -> 9186 | ... M81: =IFERROR(CFS!O13,0) -> 0
B82: Investments purchased | C82: =IFERROR(CFS!E14,0) -> -715334 | D82: =IFERROR(CFS!F14,0) -> -654760 | E82: =IFERROR(CFS!G14,0) -> -533984 | F82: =IFERROR(CFS!H14,0) -> -1107439 | G82: =IFERROR(CFS!I14,0) -> -1156843 | H82: =IFERROR(CFS!J14,0) -> -689866 | I82: =IFERROR(CFS!K14,0) -> -667878 | J82: =IFERROR(CFS!L14,0) -> -471822 | ... M82: =IFERROR(CFS!O14,0) -> 0
B83: Investments sold | C83: =IFERROR(CFS!E15,0) -> 721182 | D83: =IFERROR(CFS!F15,0) -> 663990 | E83: =IFERROR(CFS!G15,0) -> 537504 | F83: =IFERROR(CFS!H15,0) -> 1103615 | G83: =IFERROR(CFS!I15,0) -> 1174796 | H83: =IFERROR(CFS!J15,0) -> 642551 | I83: =IFERROR(CFS!K15,0) -> 668137 | J83: =IFERROR(CFS!L15,0) -> 501266 | ... M83: =IFERROR(CFS!O15,0) -> 0
B84: Interest received | C84: =IFERROR(CFS!E16,0) -> 2942 | D84: =IFERROR(CFS!F16,0) -> 1110 | E84: =IFERROR(CFS!G16,0) -> 1310 | F84: =IFERROR(CFS!H16,0) -> 972 | G84: =IFERROR(CFS!I16,0) -> 1441 | H84: =IFERROR(CFS!J16,0) -> 8400 | I84: =IFERROR(CFS!K16,0) -> 5933 | J84: =IFERROR(CFS!L16,0) -> 11103 | ... M84: =IFERROR(CFS!O16,0) -> 0
B85: Dividends received | C85: =IFERROR(CFS!E17,0) -> 732 | D85: =IFERROR(CFS!F17,0) -> 345 | E85: =IFERROR(CFS!G17,0) -> 1021 | F85: =IFERROR(CFS!H17,0) -> 501 | G85: =IFERROR(CFS!I17,0) -> 78 | H85: =IFERROR(CFS!J17,0) -> 26 | I85: =IFERROR(CFS!K17,0) -> 19 | J85: =IFERROR(CFS!L17,0) -> 20 | ... M85: =IFERROR(CFS!O17,0) -> 0
B86: Other investing items | C86: =IFERROR(CFS!E18,0) -> 846 | D86: =IFERROR(CFS!F18,0) -> -259 | E86: =IFERROR(CFS!G18,0) -> -1089 | F86: =IFERROR(CFS!H18,0) -> 621 | G86: =IFERROR(CFS!I18,0) -> -16416 | H86: =IFERROR(CFS!J18,0) -> 22 | I86: =IFERROR(CFS!K18,0) -> -18365 | J86: =IFERROR(CFS!L18,0) -> -1766 | ... M86: =IFERROR(CFS!O18,0) -> 0
B87: Cash from Investing Activity | C87: =SUM(C80:C86) -> -36186 | D87: =SUM(D80:D86) -> -66201 | E87: =SUM(E80:E86) -> -68192 | F87: =SUM(F80:F86) -> -94507 | G87: =SUM(G80:G86) -> -72497 | H87: =SUM(H80:H86) -> -142385 | I87: =SUM(I80:I86) -> -109162 | J87: =SUM(J80:J86) -> -93001 | ... L87: =SUM(L80:L86) -> -137535 | M87: =IFERROR(CFS!O19,0) -> 0
B89: Financing Activity
B90: Proceeds from shares | C90: =IFERROR(CFS!E20,0) -> 288 | D90: =IFERROR(CFS!F20,0) -> 811 | E90: =IFERROR(CFS!G20,0) -> 406 | F90: =IFERROR(CFS!H20,0) -> 230 | G90: =IFERROR(CFS!I20,0) -> 129 | H90: =IFERROR(CFS!J20,0) -> 5 | I90: =IFERROR(CFS!K20,0) -> 455 | J90: =IFERROR(CFS!L20,0) -> 479 | ... M90: =IFERROR(CFS!O20,0) -> 0
B91: Proceeds from borrowings | C91: =IFERROR(CFS!E21,0) -> 34673 | D91: =IFERROR(CFS!F21,0) -> 31728 | E91: =IFERROR(CFS!G21,0) -> 36970 | F91: =IFERROR(CFS!H21,0) -> 106701 | G91: =IFERROR(CFS!I21,0) -> 53760 | H91: =IFERROR(CFS!J21,0) -> 46421 | I91: =IFERROR(CFS!K21,0) -> 59343 | J91: =IFERROR(CFS!L21,0) -> 67134 | ... M91: =IFERROR(CFS!O21,0) -> 0
B92: Repayment of borrowings | C92: =IFERROR(CFS!E22,0) -> -21693 | D92: =IFERROR(CFS!F22,0) -> -18542 | E92: =IFERROR(CFS!G22,0) -> -19813 | F92: =IFERROR(CFS!H22,0) -> -20245 | G92: =IFERROR(CFS!I22,0) -> -18179 | H92: =IFERROR(CFS!J22,0) -> -116921 | I92: =IFERROR(CFS!K22,0) -> -49493 | J92: =IFERROR(CFS!L22,0) -> -29059 | ... M92: =IFERROR(CFS!O22,0) -> 0
B93: Interest paid fin | C93: =IFERROR(CFS!E23,0) -> -9224 | D93: =IFERROR(CFS!F23,0) -> -12920 | E93: =IFERROR(CFS!G23,0) -> -17669 | F93: =IFERROR(CFS!H23,0) -> -23338 | G93: =IFERROR(CFS!I23,0) -> -28508 | H93: =IFERROR(CFS!J23,0) -> -18340 | I93: =IFERROR(CFS!K23,0) -> -26349 | J93: =IFERROR(CFS!L23,0) -> -21650 | ... M93: =IFERROR(CFS!O23,0) -> 0
B94: Dividends paid | C94: =IFERROR(CFS!E24,0) -> -7259 | D94: =IFERROR(CFS!F24,0) -> -53 | E94: =IFERROR(CFS!G24,0) -> -3916 | F94: =IFERROR(CFS!H24,0) -> -4282 | G94: =IFERROR(CFS!I24,0) -> -4592 | H94: =IFERROR(CFS!J24,0) -> -3921 | I94: =IFERROR(CFS!K24,0) -> -4297 | J94: =IFERROR(CFS!L24,0) -> -5083 | ... M94: =IFERROR(CFS!O24,0) -> 0
B95: Financial liabilities | C95: =IFERROR(CFS!E25,0) -> 0 | D95: =IFERROR(CFS!F25,0) -> 0 | E95: =IFERROR(CFS!G25,0) -> 0 | F95: =IFERROR(CFS!H25,0) -> 0 | G95: =IFERROR(CFS!I25,0) -> -1062 | H95: =IFERROR(CFS!J25,0) -> -1022 | I95: =IFERROR(CFS!K25,0) -> -2132 | J95: =IFERROR(CFS!L25,0) -> -1406 | ... M95: =IFERROR(CFS!O25,0) -> 0
B96: Share application money | C96: =IFERROR(CFS!E26,0) -> 8 | D96: =IFERROR(CFS!F26,0) -> 4 | E96: =IFERROR(CFS!G26,0) -> 15 | F96: =IFERROR(CFS!H26,0) -> 2 | G96: =IFERROR(CFS!I26,0) -> 1 | H96: =IFERROR(CFS!J26,0) -> 0 | I96: =IFERROR(CFS!K26,0) -> 0 | J96: =IFERROR(CFS!L26,0) -> 0 | ... M96: =IFERROR(CFS!O26,0) -> 0
B97: Other financing items | C97: =IFERROR(CFS!E27,0) -> -3 | D97: =IFERROR(CFS!F27,0) -> 7589 | E97: =IFERROR(CFS!G27,0) -> 2006 | F97: =IFERROR(CFS!H27,0) -> -3162 | G97: =IFERROR(CFS!I27,0) -> -4090 | H97: =IFERROR(CFS!J27,0) -> 195682 | I97: =IFERROR(CFS!K27,0) -> 39762 | J97: =IFERROR(CFS!L27,0) -> 40 | ... M97: =IFERROR(CFS!O27,0) -> 0
B98: Cash from Financing Activity | C98: =SUM(C90:C97) -> -3210 | D98: =SUM(D90:D97) -> 8617 | E98: =SUM(E90:E97) -> -2001 | F98: =SUM(F90:F97) -> 55906 | G98: =SUM(G90:G97) -> -2541 | H98: =SUM(H90:H97) -> 101904 | I98: =SUM(I90:I97) -> 17289 | J98: =SUM(J90:J97) -> 10455 | ... M98: =SUM(M90:M97) -> 0
B100: Net Cash Flow | C100: =SUM(C77,C87,C98) -> 6567 | D100: =SUM(D77,D87,D98) -> 7429 | E100: =SUM(E77,E87,E98) -> 19804 | F100: =SUM(F77,F87,F98) -> -25037 | G100: =SUM(G77,G87,G98) -> 37755 | H100: =SUM(H77,H87,H98) -> -63481 | I100: =SUM(I77,I87,I98) -> 19506 | J100: =SUM(J77,J87,J98) -> 12852 | ... N100: =SUM(N77,N87,N98) -> 0

Sheet Data Sheet
A1: COMPANY NAME | B1: RELIANCE INDUSTRIES LTD | E1: =IF(B2<>B3, "A NEW VERSION OF THE WORKSHEET IS AVAILABLE", "")
A2: LATEST VERSION | B2: 2.1 | E2: PLEASE DO NOT MAKE ANY CHANGES TO THIS SHEET
A3: CURRENT VERSION | B3: 2.1
A5: META
A6: Number of shares | B6: =IF(B9>0, B9/B8, 0) -> 1353.1557
A7: Face Value | B7: 10
A8: Current Price | B8: 1452.8
A9: Market Capitalization | B9: 1965864.5
A15: PROFIT & LOSS
A16: Report Date | B16: 42460 | C16: 42825 | D16: 43190 | E16: 43555 | F16: 43921 | G16: 44286 | H16: 44651 | I16: 45016 | J16: 45382 | K16: 45747
A17: Sales | B17: 272583 | C17: 303954 | D17: 390823 | E17: 568337 | F17: 596679 | G17: 466307 | H17: 694673 | I17: 876396 | J17: 899041 | K17: 962820
A18: Raw Material Cost | B18: 186254 | C18: 217518 | D18: 276076 | E18: 399167 | F18: 410288 | G18: 301765 | H18: 494449 | I18: 618746 | J18: 590226 | K18: 644813
A19: Change in Inventory | B19: -2560 | C19: 5218 | D19: 8610 | E19: 4680 | F19: 5048 | G19: 9064 | H19: 21457 | I19: 30263 | J19: 4883 | K19: 15124
A20: Power and Fuel | B20: 10741 | C20: 11251 | D20: 14569 | E20: 17029 | F20: 15098 | G20: 13214 | H20: 17902 | I20: 25062 | J20: 22137 | K20: 23823
A21: Other Mfr. Exp | B21: 8272 | C21: 9909 | D21: 9691 | E21: 12198 | F21: 11434 | G21: 7687 | H21: 12174 | I21: 19658 | J21: 18276 | K21: 18358
A22: Employee Cost | B22: 7407 | C22: 8388 | D22: 9523 | E22: 12488 | F22: 14075 | G22: 14817 | H22: 18758 | I22: 24872 | J22: 25679 | K22: 28559
A23: Selling and admin | B23: 18808 | C23: 18520 | D23: 29111 | E23: 50221 | F23: 62622 | G23: 56154 | H23: 63513 | I23: 67369 | J23: 77292 | K23: 88760
A24: Other Expenses | B24: -3240 | C24: -2721 | D24: -3852 | E24: -2336 | F24: -1056 | G24: 944 | H24: 753 | I24: 8634 | J24: 7816 | K24: 8033
A25: Other Income | B25: 12212 | C25: 9222 | D25: 9869 | E25: 8406 | F25: 8570 | G25: 22432 | H25: 19600 | I25: 12020 | J25: 15792 | K25: 17824
A26: Depreciation | B26: 11565 | C26: 11646 | D26: 16706 | E26: 20934 | F26: 22203 | G26: 26572 | H26: 29782 | I26: 40303 | J26: 50832 | K26: 53136
A27: Interest | B27: 3691 | C27: 3849 | D27: 8052 | E27: 16495 | F27: 22027 | G27: 21189 | H27: 14584 | I27: 19571 | J27: 23118 | K27: 24269
... A31: Dividend Amount | B31: 3095.4 | C31: 3254.9 | D31: 3553.2 | E31: 3851.9 | F31: 4120.35 | G31: 4511.5 | H31: 5412 | I31: 6089.4 | J31: 6766 | K31: 7442.6
A40: Quarters
A41: Report Date | B41: 45107 | C41: 45199 | D41: 45291 | E41: 45382 | F41: 45473 | G41: 45565 | H41: 45657 | I41: 45747 | J41: 45838 | K41: 45930
A42: Sales | B42: 207559 | C42: 231886 | D42: 225086 | E42: 236533 | F42: 231784 | G42: 231535 | H42: 239986 | I42: 261388 | J42: 243632 | K42: 254623
A43: Expenses | B43: 169466 | C43: 190918 | D43: 184430 | E43: 194017 | F43: 193019 | G43: 192477 | H43: 196197 | I43: 217556 | J43: 200727 | K43: 208738
A44: Other Income | B44: 3813 | C44: 3841 | D44: 3869 | E44: 4534 | F44: 3983 | G44: 4876 | H44: 4214 | I44: 4905 | J44: 15119 | K44: 4482
A45: Depreciation | B45: 11775 | C45: 12585 | D45: 12903 | E45: 13569 | F45: 13596 | G45: 12880 | H45: 13181 | I45: 13479 | J45: 13842 | K45: 14416
A46: Interest | B46: 5837 | C46: 5731 | D46: 5789 | E46: 5761 | F46: 5918 | G46: 6017 | H46: 6179 | I46: 6155 | J46: 7036 | K46: 6827
A47: Profit before tax | B47: 24294 | C47: 26493 | D47: 25833 | E47: 27720 | F47: 23234 | G47: 25037 | H47: 28643 | I47: 29103 | J47: 37146 | K47: 29124
A48: Tax | B48: 6112 | C48: 6673 | D48: 6345 | E48: 6577 | F48: 5786 | G48: 5936 | H48: 6839 | I48: 6669 | J48: 6465 | K48: 6978
A49: Net profit | B49: 16011 | C49: 17394 | D49: 17265 | E49: 18951 | F49: 15138 | G49: 16563 | H49: 18540 | I49: 19407 | J49: 26994 | K49: 18165
A50: Operating Profit | B50: 38093 | C50: 40968 | D50: 40656 | E50: 42516 | F50: 38765 | G50: 39058 | H50: 43789 | I50: 43832 | J50: 42905 | K50: 45885
A55: BALANCE SHEET
A56: Report Date | B56: 42460 | C56: 42825 | D56: 43190 | E56: 43555 | F56: 43921 | G56: 44286 | H56: 44651 | I56: 45016 | J56: 45382 | K56: 45747
A57: Equity Share Capital | B57: 2948 | C57: 2959 | D57: 5922 | E57: 5926 | F57: 6339 | G57: 6445 | H57: 6765 | I57: 6766 | J57: 6766 | K57: 13532
A58: Reserves | B58: 228608 | C58: 260750 | D58: 287584 | E58: 381186 | F58: 442827 | G58: 693727 | H58: 772720 | I58: 709106 | J58: 786715 | K58: 829668
A59: Borrowings | B59: 194714 | C59: 217475 | D59: 239843 | E59: 307714 | F59: 355133 | G59: 278962 | H59: 319158 | I59: 451664 | J59: 350719 | K59: 374313
A60: Other Liabilities | B60: 172727 | C60: 225618 | D60: 277924 | E60: 302804 | F60: 358716 | G60: 340931 | H60: 399979 | I60: 438346 | J60: 610848 | K60: 732200
A61: Total | B61: 598997 | C61: 706802 | D61: 811273 | E61: 997630 | F61: 1163015 | G61: 1320065 | H61: 1498622 | I61: 1605882 | J61: 1755048 | K61: 1949713
A62: Net Block | B62: 184910 | C62: 198526 | D62: 403885 | E62: 398374 | F62: 532658 | G62: 541258 | H62: 627798 | I62: 724805 | J62: 779985 | K62: 999393
A63: Capital Work in Progress | B63: 228697 | C63: 324837 | D63: 187022 | E63: 179463 | F63: 109106 | G63: 125953 | H63: 172506 | I63: 293752 | J63: 338855 | K63: 262358
A64: Investments | B64: 84015 | C64: 82899 | D64: 82862 | E64: 235635 | F64: 276767 | G64: 364828 | H64: 394264 | I64: 235560 | J64: 225672 | K64: 242381
A65: Other Assets | B65: 101375 | C65: 100540 | D65: 137504 | E65: 184158 | F65: 244484 | G65: 288026 | H65: 304054 | I65: 351765 | J65: 410536 | K65: 445581
A66: Total | B66: 598997 | C66: 706802 | D66: 811273 | E66: 997630 | F66: 1163015 | G66: 1320065 | H66: 1498622 | I66: 1605882 | J66: 1755048 | K66: 1949713
A67: Receivables | B67: 4465 | C67: 8177 | D67: 17555 | E67: 30089 | F67: 19656 | G67: 19014 | H67: 23640 | I67: 28448 | J67: 31628 | K67: 42121
... A70: No. of Equity Shares | B70: 2948021694 | C70: 2958924277 | D70: 5921826196 | E70: 5925868997 | F70: 6338693823 | G70: 6762068814 | H70: 6765994014 | I70: 6766094014 | J70: 6766094014 | K70: 13532515463
A71: New Bonus Shares | D71: 2959863235 | E71: 2959863235 | K71: 6766186449
A72: Face value | B72: 10 | C72: 10 | D72: 10 | E72: 10 | F72: 10 | G72: 10 | H72: 10 | I72: 10 | J72: 10 | K72: 10
A80: CASH FLOW:
A81: Report Date | B81: 42460 | C81: 42825 | D81: 43190 | E81: 43555 | F81: 43921 | G81: 44286 | H81: 44651 | I81: 45016 | J81: 45382 | K81: 45747
A82: Cash from Operating Activity | B82: 38134 | C82: 49550 | D82: 71459 | E82: 42346 | F82: 94877 | G82: 26958 | H82: 110654 | I82: 115032 | J82: 158788 | K82: 178703
A83: Cash from Investing Activity | B83: -36186 | C83: -66201 | D83: -68192 | E83: -94507 | F83: -72497 | G83: -142385 | H83: -109162 | I83: -93001 | J83: -113581 | K83: -137535
A84: Cash from Financing Activity | B84: -3210 | C84: 8617 | D84: -2001 | E84: 55906 | F84: -2541 | G84: 101904 | H84: 17289 | I84: 10455 | J84: -16646 | K84: -31891
A85: Net Cash Flow | B85: -1262 | C85: -8034 | D85: 1266 | E85: 3745 | F85: 19839 | G85: -13523 | H85: 18781 | I85: 32486 | J85: 28561 | K85: 9277
A90: PRICE: | B90: 237.46 | C90: 300.09 | D90: 401.08 | E90: 619.43 | F90: 506.06 | G90: 918.78 | H90: 1208.51 | I90: 1069.21 | J90: 1485.85 | K90: 1275.1
A92: DERIVED:
A93: Adjusted Equity Shares in Cr | B93: 1382.58 | C93: 1387.22 | D93: 1351.39 | E93: 1352.26 | F93: 1352.37 | G93: 1267.89 | H93: 1352.98 | I93: 1353.12 | J93: 1353.14 | K93: 1353.24

Sheet Ratio Analysis
B2: ="Ratio Analysis of - "&'[1]Data Sheet'!B1 -> Ratio Analysis of - RELIANCE INDUSTRIES LTD
B3: YEARS | C3: =IFERROR('Data Sheet'!B16,0) -> 42460 | D3: =IFERROR('Data Sheet'!C16,0) -> 42825 | E3: =IFERROR('Data Sheet'!D16,0) -> 43190 | F3: =IFERROR('Data Sheet'!E16,0) -> 43555 | G3: =IFERROR('Data Sheet'!F16,0) -> 43921 | H3: =IFERROR('Data Sheet'!G16,0) -> 44286 | I3: =IFERROR('Data Sheet'!H16,0) -> 44651 | J3: =IFERROR('Data Sheet'!I16,0) -> 45016 | ... L3: =IFERROR('Data Sheet'!K16,0) -> 45747 | M3: Trend | N3: Mean | O3: Median
B4: Sales Growth | C4: =IFERROR('HISTORICAL FS'!C5,0) -> - | D4: =IFERROR('HISTORICAL FS'!D5,0) -> 0.11508788 | E4: =IFERROR('HISTORICAL FS'!E5,0) -> 0.28579654 | F4: =IFERROR('HISTORICAL FS'!F5,0) -> 0.45420561 | G4: =IFERROR('HISTORICAL FS'!G5,0) -> 0.0498683 | H4: =IFERROR('HISTORICAL FS'!H5,0) -> -0.21849604 | I4: =IFERROR('HISTORICAL FS'!I5,0) -> 0.48973316 | J4: =IFERROR('HISTORICAL FS'!J5,0) -> 0.26159502 | ... L4: =IFERROR('HISTORICAL FS'!L5,0) -> 0.070941147 | N4: =AVERAGE(D4:L4) -> 0.17050782 | O4: =MEDIAN(D4:L4) -> 0.11508788
B5: EBIDTA Growth | D5: =IFERROR('HISTORICAL FS'!D16/'HISTORICAL FS'!C16-1,0) -> 0.10832675 | E5: =IFERROR('HISTORICAL FS'!E16/'HISTORICAL FS'!D16-1,0) -> 0.38888289 | F5: =IFERROR('HISTORICAL FS'!F16/'HISTORICAL FS'!E16-1,0) -> 0.3099588 | G5: =IFERROR('HISTORICAL FS'!G16/'HISTORICAL FS'!F16-1,0) -> 0.059537092 | H5: =IFERROR('HISTORICAL FS'!H16/'HISTORICAL FS'!G16-1,0) -> -0.094952165 | I5: =IFERROR('HISTORICAL FS'!I16/'HISTORICAL FS'!H16-1,0) -> 0.34399059 | J5: =IFERROR('HISTORICAL FS'!J16/'HISTORICAL FS'!I16-1,0) -> 0.31070813 | K5: =IFERROR('HISTORICAL FS'!K16/'HISTORICAL FS'!J16-1,0) -> 0.14179513 | L5: =IFERROR('HISTORICAL FS'!L16/'HISTORICAL FS'!K16-1,0) -> 0.019077158 | N5: =AVERAGE(D5:L5) -> 0.17636938 | O5: =MEDIAN(D5:L5) -> 0.14179513
B6: EBT Growth | D6: =IFERROR('HISTORICAL FS'!D25/'HISTORICAL FS'!C25-1,0) -> 0.16162111 | E6: =IFERROR('HISTORICAL FS'!E25/'HISTORICAL FS'!D25-1,0) -> 0.28381799 | F6: =IFERROR('HISTORICAL FS'!F25/'HISTORICAL FS'!E25-1,0) -> 0.18363374 | G6: =IFERROR('HISTORICAL FS'!G25/'HISTORICAL FS'!F25-1,0) -> -0.038123919 | H6: =IFERROR('HISTORICAL FS'!H25/'HISTORICAL FS'!G25-1,0) -> -0.26660894 | I6: =IFERROR('HISTORICAL FS'!I25/'HISTORICAL FS'!H25-1,0) -> 0.94420055 | J6: =IFERROR('HISTORICAL FS'!J25/'HISTORICAL FS'!I25-1,0) -> 0.28387448 | K6: =IFERROR('HISTORICAL FS'!K25/'HISTORICAL FS'!J25-1,0) -> 0.074038135 | L6: =IFERROR('HISTORICAL FS'!L25/'HISTORICAL FS'!K25-1,0) -> -0.004009125 | N6: =AVERAGE(D6:L6) -> 0.18027156 | O6: =MEDIAN(D6:L6) -> 0.16162111
B7: Net profit Growth | D7: =IFERROR('HISTORICAL FS'!D31/'HISTORICAL FS'!C31-1,0) -> 0.16782821 | E7: =IFERROR('HISTORICAL FS'!E31/'HISTORICAL FS'!D31-1,0) -> 0.27169958 | F7: =IFERROR('HISTORICAL FS'!F31/'HISTORICAL FS'!E31-1,0) -> 0.19915303 | G7: =IFERROR('HISTORICAL FS'!G31/'HISTORICAL FS'!F31-1,0) -> -0.0038497025 | H7: =IFERROR('HISTORICAL FS'!H31/'HISTORICAL FS'!G31-1,0) -> -9.5816033e-05 | I7: =IFERROR('HISTORICAL FS'!I31/'HISTORICAL FS'!H31-1,0) -> 0.54102916 | J7: =IFERROR('HISTORICAL FS'!J31/'HISTORICAL FS'!I31-1,0) -> 0.28651674 | K7: =IFERROR('HISTORICAL FS'!K31/'HISTORICAL FS'!J31-1,0) -> 0.012454083 | L7: =IFERROR('HISTORICAL FS'!L31/'HISTORICAL FS'!K31-1,0) -> 0.0019414077 | N7: =AVERAGE(D7:L7) -> 0.16407519 | O7: =MEDIAN(D7:L7) -> 0.16782821
B8: Dividend Growth | D8: =IFERROR('HISTORICAL FS'!D39/'HISTORICAL FS'!C39-1,0) -> 0.048010903 | E8: =IFERROR('HISTORICAL FS'!E39/'HISTORICAL FS'!D39-1,0) -> 0.12058975 | F8: =IFERROR('HISTORICAL FS'!F39/'HISTORICAL FS'!E39-1,0) -> 0.083367616 | G8: =IFERROR('HISTORICAL FS'!G39/'HISTORICAL FS'!F39-1,0) -> 0.069605871 | H8: =IFERROR('HISTORICAL FS'!H39/'HISTORICAL FS'!G39-1,0) -> 0.16788695 | I8: =IFERROR('HISTORICAL FS'!I39/'HISTORICAL FS'!H39-1,0) -> 0.12415715 | J8: =IFERROR('HISTORICAL FS'!J39/'HISTORICAL FS'!I39-1,0) -> 0.12504988 | K8: =IFERROR('HISTORICAL FS'!K39/'HISTORICAL FS'!J39-1,0) -> 0.11109469 | L8: =IFERROR('HISTORICAL FS'!L39/'HISTORICAL FS'!K39-1,0) -> 0.099918714 | N8: =AVERAGE(D8:L8) -> 0.10552017 | O8: =MEDIAN(D8:L8) -> 0.11109469
B10: Gross Margin | C10: ='HISTORICAL FS'!C11 -> 0.21039096 | D10: ='HISTORICAL FS'!D11 -> 0.20432697 | E10: ='HISTORICAL FS'!E11 -> 0.22919327 | F10: ='HISTORICAL FS'!F11 -> 0.2324941 | G10: ='HISTORICAL FS'!G11 -> 0.25278584 | H10: ='HISTORICAL FS'!H11 -> 0.29570219 | I10: ='HISTORICAL FS'!I11 -> 0.24881779 | J10: ='HISTORICAL FS'!J11 -> 0.24911227 | ... L10: ='HISTORICAL FS'!L11 -> 0.27252342 | N10: =IFERROR(AVERAGE(C10:L10),0) -> 0.24707581 | O10: =IFERROR(MEDIAN(C10:L10),0) -> 0.24896503
B11: EBIDTA Margin | C11: ='HISTORICAL FS'!C17 -> 0.15327808 | D11: ='HISTORICAL FS'!D17 -> 0.15234871 | E11: ='HISTORICAL FS'!E17 -> 0.16456299 | F11: ='HISTORICAL FS'!F17 -> 0.14823951 | G11: ='HISTORICAL FS'!G17 -> 0.14960473 | H11: ='HISTORICAL FS'!H17 -> 0.17325496 | I11: ='HISTORICAL FS'!I17 -> 0.1563052 | J11: ='HISTORICAL FS'!J17 -> 0.16239006 | ... L11: ='HISTORICAL FS'!L17 -> 0.17199269 | N11: =IFERROR(AVERAGE(C11:L11),0) -> 0.16127229 | O11: =IFERROR(MEDIAN(C11:L11),0) -> 0.15934763
B12: EBIT Margin | C12: =IFERROR('HISTORICAL FS'!C16-'HISTORICAL FS'!C22,0)/'HISTORICAL FS'!C4 -> 0.11085064 | D12: =IFERROR('HISTORICAL FS'!D16-'HISTORICAL FS'!D22,0)/'HISTORICAL FS'!D4 -> 0.1140337 | E12: =IFERROR('HISTORICAL FS'!E16-'HISTORICAL FS'!E22,0)/'HISTORICAL FS'!E4 -> 0.12181729 | F12: =IFERROR('HISTORICAL FS'!F16-'HISTORICAL FS'!F22,0)/'HISTORICAL FS'!F4 -> 0.11140573 | G12: =IFERROR('HISTORICAL FS'!G16-'HISTORICAL FS'!G22,0)/'HISTORICAL FS'!G4 -> 0.11239377 | H12: =IFERROR('HISTORICAL FS'!H16-'HISTORICAL FS'!H22,0)/'HISTORICAL FS'!H4 -> 0.11627104 | I12: =IFERROR('HISTORICAL FS'!I16-'HISTORICAL FS'!I22,0)/'HISTORICAL FS'!I4 -> 0.11343323 | J12: =IFERROR('HISTORICAL FS'!J16-'HISTORICAL FS'!J22,0)/'HISTORICAL FS'!J4 -> 0.11640286 | ... L12: =IFERROR('HISTORICAL FS'!L16-'HISTORICAL FS'!L22,0)/'HISTORICAL FS'!L4 -> 0.1168048 | N12: =IFERROR(AVERAGE(C12:L12),0) -> 0.11576187 | O12: =IFERROR(MEDIAN(C12:L12),0) -> 0.11515237
B13: EBT Margin | C13: ='HISTORICAL FS'!C26 -> 0.09730981 | D13: ='HISTORICAL FS'!D26 -> 0.1013706 | E13: ='HISTORICAL FS'!E26 -> 0.10121462 | F13: ='HISTORICAL FS'!F26 -> 0.08238246 | G13: ='HISTORICAL FS'!G26 -> 0.075477769 | H13: ='HISTORICAL FS'!H26 -> 0.070831019 | I13: ='HISTORICAL FS'!I26 -> 0.092439176 | J13: ='HISTORICAL FS'!J26 -> 0.09407163 | ... L13: ='HISTORICAL FS'!L26 -> 0.091598637 | N13: =IFERROR(AVERAGE(C13:L13),0) -> 0.090518734 | O13: =IFERROR(MEDIAN(C13:L13),0) -> 0.093255403
B14: Net Profit Margin | C14: ='HISTORICAL FS'!C32 -> 0.064747251 | D14: ='HISTORICAL FS'!D32 -> 0.067809603 | E14: ='HISTORICAL FS'!E32 -> 0.067066166 | F14: ='HISTORICAL FS'!F32 -> 0.055303456 | G14: ='HISTORICAL FS'!G32 -> 0.052473776 | H14: ='HISTORICAL FS'!H32 -> 0.067138173 | I14: ='HISTORICAL FS'!I32 -> 0.069449943 | J14: ='HISTORICAL FS'!J32 -> 0.070821866 | ... L14: ='HISTORICAL FS'!L32 -> 0.065394362 | N14: =IFERROR(AVERAGE(C14:L14),0) -> 0.065010241 | O14: =IFERROR(MEDIAN(C14:L14),0) -> 0.067102169
B16: SalesExpenses%Sales | C16: ='HISTORICAL FS'!C14 -> 0.057112879 | D16: ='HISTORICAL FS'!D14 -> 0.05197826 | E16: ='HISTORICAL FS'!E14 -> 0.06463028 | F16: ='HISTORICAL FS'!F14 -> 0.084254588 | G16: ='HISTORICAL FS'!G14 -> 0.10318111 | H16: ='HISTORICAL FS'!H14 -> 0.12244723 | I16: ='HISTORICAL FS'!I14 -> 0.092512592 | J16: ='HISTORICAL FS'!J14 -> 0.086722212 | ... L16: ='HISTORICAL FS'!L14 -> 0.10053073 | N16: =IFERROR(AVERAGE(C16:L16),0) -> 0.08580352 | O16: =IFERROR(MEDIAN(C16:L16),0) -> 0.089617402
B17: Depreciation%Sales | C17: ='HISTORICAL FS'!C23 -> 0.042427444 | D17: ='HISTORICAL FS'!D23 -> 0.038315008 | E17: ='HISTORICAL FS'!E23 -> 0.042745693 | F17: ='HISTORICAL FS'!F23 -> 0.03683378 | G17: ='HISTORICAL FS'!G23 -> 0.037210963 | H17: ='HISTORICAL FS'!H23 -> 0.056983918 | I17: ='HISTORICAL FS'!I23 -> 0.04287197 | J17: ='HISTORICAL FS'!J23 -> 0.045987202 | ... L17: ='HISTORICAL FS'!L23 -> 0.055187886 | N17: =IFERROR(AVERAGE(C17:L17),0) -> 0.045510411 | O17: =IFERROR(MEDIAN(C17:L17),0) -> 0.042808832
B18: Operatingincome%Sales | C18: =C12 -> 0.11085064 | D18: =D12 -> 0.1140337 | E18: =E12 -> 0.12181729 | F18: =F12 -> 0.11140573 | G18: =G12 -> 0.11239377 | H18: =H12 -> 0.11627104 | I18: =I12 -> 0.11343323 | J18: =J12 -> 0.11640286 | ... L18: =L12 -> 0.1168048 | N18: =IFERROR(AVERAGE(C18:L18),0) -> 0.11576187 | O18: =IFERROR(MEDIAN(C18:L18),0) -> 0.11515237
B20: Return on Capital Employed | C20: =('HISTORICAL FS'!C16-'HISTORICAL FS'!C22)/(SUM('HISTORICAL FS'!C47,'HISTORICAL FS'!C48,'HISTORICAL FS'!C49)) -> 0.070884651 | D20: =('HISTORICAL FS'!D16-'HISTORICAL FS'!D22)/(SUM('HISTORICAL FS'!D47,'HISTORICAL FS'!D48,'HISTORICAL FS'!D49)) -> 0.072032736 | E20: =('HISTORICAL FS'!E16-'HISTORICAL FS'!E22)/(SUM('HISTORICAL FS'!E47,'HISTORICAL FS'!E48,'HISTORICAL FS'!E49)) -> 0.089264253 | F20: =('HISTORICAL FS'!F16-'HISTORICAL FS'!F22)/(SUM('HISTORICAL FS'!F47,'HISTORICAL FS'!F48,'HISTORICAL FS'!F49)) -> 0.091124972 | G20: =('HISTORICAL FS'!G16-'HISTORICAL FS'!G22)/(SUM('HISTORICAL FS'!G47,'HISTORICAL FS'!G48,'HISTORICAL FS'!G49)) -> 0.083380683 | H20: =('HISTORICAL FS'!H16-'HISTORICAL FS'!H22)/(SUM('HISTORICAL FS'!H47,'HISTORICAL FS'!H48,'HISTORICAL FS'!H49)) -> 0.055373422 | I20: =('HISTORICAL FS'!I16-'HISTORICAL FS'!I22)/(SUM('HISTORICAL FS'!I47,'HISTORICAL FS'!I48,'HISTORICAL FS'!I49)) -> 0.071723936 | J20: =('HISTORICAL FS'!J16-'HISTORICAL FS'!J22)/(SUM('HISTORICAL FS'!J47,'HISTORICAL FS'!J48,'HISTORICAL FS'!J49)) -> 0.087376321 | ... L20: =('HISTORICAL FS'!L16-'HISTORICAL FS'!L22)/(SUM('HISTORICAL FS'!L47,'HISTORICAL FS'!L48,'HISTORICAL FS'!L49)) -> 0.092370266 | N20: =IFERROR(AVERAGE(C20:L20),0) -> 0.081112432 | O20: =IFERROR(MEDIAN(C20:L20),0) -> 0.085378502
B21: Retained Earnings % | C21: =IFERROR('HISTORICAL FS'!C43,0) -> 0.82461329 | D21: =IFERROR('HISTORICAL FS'!D43,0) -> 0.84207947 | E21: =IFERROR('HISTORICAL FS'!E43,0) -> 0.86443859 | F21: =IFERROR('HISTORICAL FS'!F43,0) -> 0.87744902 | G21: =IFERROR('HISTORICAL FS'!G43,0) -> 0.86840147 | H21: =IFERROR('HISTORICAL FS'!H43,0) -> 0.85589485 | I21: =IFERROR('HISTORICAL FS'!I43,0) -> 0.88782257 | J21: =IFERROR('HISTORICAL FS'!J43,0) -> 0.90189147 | ... L21: =IFERROR('HISTORICAL FS'!L43,0) -> 0.88179407 | N21: =IFERROR(AVERAGE(C21:L21),0) -> 0.86967162 | O21: =IFERROR(MEDIAN(C21:L21),0) -> 0.87292524
B22: Return on Equity % | C22: =IFERROR('HISTORICAL FS'!C31/SUM('HISTORICAL FS'!C47,'HISTORICAL FS'!C48),0) -> 0.076219144 | D22: =IFERROR('HISTORICAL FS'!D31/SUM('HISTORICAL FS'!D47,'HISTORICAL FS'!D48),0) -> 0.078158121 | E22: =IFERROR('HISTORICAL FS'!E31/SUM('HISTORICAL FS'!E47,'HISTORICAL FS'!E48),0) -> 0.089303115 | F22: =IFERROR('HISTORICAL FS'!F31/SUM('HISTORICAL FS'!F47,'HISTORICAL FS'!F48),0) -> 0.081193556 | G22: =IFERROR('HISTORICAL FS'!G31/SUM('HISTORICAL FS'!G47,'HISTORICAL FS'!G48),0) -> 0.069706968 | H22: =IFERROR('HISTORICAL FS'!H31/SUM('HISTORICAL FS'!H47,'HISTORICAL FS'!H48),0) -> 0.044713299 | I22: =IFERROR('HISTORICAL FS'!I31/SUM('HISTORICAL FS'!I47,'HISTORICAL FS'!I48),0) -> 0.06189343 | J22: =IFERROR('HISTORICAL FS'!J31/SUM('HISTORICAL FS'!J47,'HISTORICAL FS'!J48),0) -> 0.086702651 | ... L22: =IFERROR('HISTORICAL FS'!L31/SUM('HISTORICAL FS'!L47,'HISTORICAL FS'!L48),0) -> 0.07467149 | N22: =IFERROR(AVERAGE(C22:L22),0) -> 0.074175838 | O22: =IFERROR(MEDIAN(C22:L22),0) -> 0.077188632
B23: Self Sustained Growth Rate | C23: =C22*C21 -> 0.062851319 | D23: =D22*D21 -> 0.065815349 | E23: =E22*E21 -> 0.077197059 | F23: =F22*F21 -> 0.071243206 | G23: =G22*G21 -> 0.060533633 | H23: =H22*H21 -> 0.038269882 | I23: =I22*I21 -> 0.054950384 | J23: =J22*J21 -> 0.078196381 | ... L23: =L22*L21 -> 0.065844877 | N23: =IFERROR(AVERAGE(C23:L23),0) -> 0.064557171 | O23: =IFERROR(MEDIAN(C23:L23),0) -> 0.065830113
B24: Interest Coverage Ratio | C24: =('HISTORICAL FS'!C16-'HISTORICAL FS'!C22)/'HISTORICAL FS'!C19 -> 8.1863993 | D24: =('HISTORICAL FS'!D16-'HISTORICAL FS'!D22)/'HISTORICAL FS'!D19 -> 9.0051962 | E24: =('HISTORICAL FS'!E16-'HISTORICAL FS'!E22)/'HISTORICAL FS'!E19 -> 5.9126925 | F24: =('HISTORICAL FS'!F16-'HISTORICAL FS'!F22)/'HISTORICAL FS'!F19 -> 3.8384965 | G24: =('HISTORICAL FS'!G16-'HISTORICAL FS'!G22)/'HISTORICAL FS'!G19 -> 3.0445816 | H24: =('HISTORICAL FS'!H16-'HISTORICAL FS'!H22)/'HISTORICAL FS'!H19 -> 2.5587805 | I24: =('HISTORICAL FS'!I16-'HISTORICAL FS'!I22)/'HISTORICAL FS'!I19 -> 5.403113 | J24: =('HISTORICAL FS'!J16-'HISTORICAL FS'!J22)/'HISTORICAL FS'!J19 -> 5.2125594 | ... L24: =('HISTORICAL FS'!L16-'HISTORICAL FS'!L22)/'HISTORICAL FS'!L19 -> 4.6339775 | N24: =IFERROR(AVERAGE(C24:L24),0) -> 5.2626059 | O24: =IFERROR(MEDIAN(C24:L24),0) -> 5.0214108
B26: Debtor Turnover Ratio | C26: =IFERROR('HISTORICAL FS'!C4/'HISTORICAL FS'!C59,0) -> 61.048824 | D26: =IFERROR('HISTORICAL FS'!D4/'HISTORICAL FS'!D59,0) -> 37.171823 | E26: =IFERROR('HISTORICAL FS'!E4/'HISTORICAL FS'!E59,0) -> 22.262774 | F26: =IFERROR('HISTORICAL FS'!F4/'HISTORICAL FS'!F59,0) -> 18.888531 | G26: =IFERROR('HISTORICAL FS'!G4/'HISTORICAL FS'!G59,0) -> 30.356074 | H26: =IFERROR('HISTORICAL FS'!H4/'HISTORICAL FS'!H59,0) -> 24.524403 | I26: =IFERROR('HISTORICAL FS'!I4/'HISTORICAL FS'!I59,0) -> 29.385491 | J26: =IFERROR('HISTORICAL FS'!J4/'HISTORICAL FS'!J59,0) -> 30.806946 | ... L26: =IFERROR('HISTORICAL FS'!L4/'HISTORICAL FS'!L59,0) -> 22.858432 | N26: =IFERROR(AVERAGE(C26:L26),0) -> 30.572878 | O26: =IFERROR(MEDIAN(C26:L26),0) -> 28.905484
B27: Creditor Turnover Rtaio | C27: =IFERROR('HISTORICAL FS'!C4/'HISTORICAL FS'!C50,0) -> 1.5781146 | D27: =IFERROR('HISTORICAL FS'!D4/'HISTORICAL FS'!D50,0) -> 1.3472063 | E27: =IFERROR('HISTORICAL FS'!E4/'HISTORICAL FS'!E50,0) -> 1.4062226 | F27: =IFERROR('HISTORICAL FS'!F4/'HISTORICAL FS'!F50,0) -> 1.8769138 | G27: =IFERROR('HISTORICAL FS'!G4/'HISTORICAL FS'!G50,0) -> 1.6633744 | H27: =IFERROR('HISTORICAL FS'!H4/'HISTORICAL FS'!H50,0) -> 1.367746 | I27: =IFERROR('HISTORICAL FS'!I4/'HISTORICAL FS'!I50,0) -> 1.7367737 | J27: =IFERROR('HISTORICAL FS'!J4/'HISTORICAL FS'!J50,0) -> 1.9993247 | ... L27: =IFERROR('HISTORICAL FS'!L4/'HISTORICAL FS'!L50,0) -> 1.3149686 | N27: =IFERROR(AVERAGE(C27:L27),0) -> 1.5762436 | O27: =IFERROR(MEDIAN(C27:L27),0) -> 1.5249531
B28: Inventory Turnover | C28: =IFERROR('HISTORICAL FS'!C4/'HISTORICAL FS'!C60,0) -> 5.8637654 | D28: =IFERROR('HISTORICAL FS'!D4/'HISTORICAL FS'!D60,0) -> 6.2093522 | E28: =IFERROR('HISTORICAL FS'!E4/'HISTORICAL FS'!E60,0) -> 6.4241005 | F28: =IFERROR('HISTORICAL FS'!F4/'HISTORICAL FS'!F60,0) -> 8.4122053 | G28: =IFERROR('HISTORICAL FS'!G4/'HISTORICAL FS'!G60,0) -> 8.073813 | H28: =IFERROR('HISTORICAL FS'!H4/'HISTORICAL FS'!H60,0) -> 5.7095088 | I28: =IFERROR('HISTORICAL FS'!I4/'HISTORICAL FS'!I60,0) -> 6.4454063 | J28: =IFERROR('HISTORICAL FS'!J4/'HISTORICAL FS'!J60,0) -> 6.2596137 | ... L28: =IFERROR('HISTORICAL FS'!L4/'HISTORICAL FS'!L60,0) -> 6.5918583 | N28: =IFERROR(AVERAGE(C28:L28),0) -> 6.5874555 | O28: =IFERROR(MEDIAN(C28:L28),0) -> 6.3418571
B29: Fixed Asset Turnover | C29: =IFERROR('HISTORICAL FS'!C4/'HISTORICAL FS'!C53,0) -> 1.4741388 | D29: =IFERROR('HISTORICAL FS'!D4/'HISTORICAL FS'!D53,0) -> 1.5310539 | E29: =IFERROR('HISTORICAL FS'!E4/'HISTORICAL FS'!E53,0) -> 0.96765911 | F29: =IFERROR('HISTORICAL FS'!F4/'HISTORICAL FS'!F53,0) -> 1.4266418 | G29: =IFERROR('HISTORICAL FS'!G4/'HISTORICAL FS'!G53,0) -> 1.1201916 | H29: =IFERROR('HISTORICAL FS'!H4/'HISTORICAL FS'!H53,0) -> 0.86152445 | I29: =IFERROR('HISTORICAL FS'!I4/'HISTORICAL FS'!I53,0) -> 1.1065231 | J29: =IFERROR('HISTORICAL FS'!J4/'HISTORICAL FS'!J53,0) -> 1.2091473 | ... L29: =IFERROR('HISTORICAL FS'!L4/'HISTORICAL FS'!L53,0) -> 0.96340479 | N29: =IFERROR(AVERAGE(C29:L29),0) -> 1.1812924 | O29: =IFERROR(MEDIAN(C29:L29),0) -> 1.1364152
B30: Capital Turnover | C30: =IFERROR('HISTORICAL FS'!C4/SUM('HISTORICAL FS'!C47,'HISTORICAL FS'!C48),0) -> 1.1771796 | D30: =IFERROR('HISTORICAL FS'!D4/SUM('HISTORICAL FS'!D47,'HISTORICAL FS'!D48),0) -> 1.1526114 | E30: =IFERROR('HISTORICAL FS'!E4/SUM('HISTORICAL FS'!E47,'HISTORICAL FS'!E48),0) -> 1.3315673 | F30: =IFERROR('HISTORICAL FS'!F4/SUM('HISTORICAL FS'!F47,'HISTORICAL FS'!F48),0) -> 1.4681462 | G30: =IFERROR('HISTORICAL FS'!G4/SUM('HISTORICAL FS'!G47,'HISTORICAL FS'!G48),0) -> 1.3284153 | H30: =IFERROR('HISTORICAL FS'!H4/SUM('HISTORICAL FS'!H47,'HISTORICAL FS'!H48),0) -> 0.66598921 | I30: =IFERROR('HISTORICAL FS'!I4/SUM('HISTORICAL FS'!I47,'HISTORICAL FS'!I48),0) -> 0.89119483 | J30: =IFERROR('HISTORICAL FS'!J4/SUM('HISTORICAL FS'!J47,'HISTORICAL FS'!J48),0) -> 1.2242356 | ... L30: =IFERROR('HISTORICAL FS'!L4/SUM('HISTORICAL FS'!L47,'HISTORICAL FS'!L48),0) -> 1.1418643 | N30: =IFERROR(AVERAGE(C30:L30),0) -> 1.1514238 | O30: =IFERROR(MEDIAN(C30:L30),0) -> 1.1648955
B32: Debtor Days | C32: =IFERROR(365/C26,0) -> 5.9788211 | D32: =IFERROR(365/D26,0) -> 9.8192654 | E32: =IFERROR(365/E26,0) -> 16.395082 | F32: =IFERROR(365/F26,0) -> 19.323896 | G32: =IFERROR(365/G26,0) -> 12.023953 | H32: =IFERROR(365/H26,0) -> 14.883135 | I32: =IFERROR(365/I26,0) -> 12.421096 | J32: =IFERROR(365/J26,0) -> 11.847977 | ... L32: =IFERROR(365/L26,0) -> 15.96785 | N32: =IFERROR(AVERAGE(C32:L32),0) -> 13.150167 | O32: =IFERROR(MEDIAN(C32:L32),0) -> 12.630845
B33: Payable Days | C33: =IFERROR(365/C27,0) -> 231.28865 | D33: =IFERROR(365/D27,0) -> 270.93103 | E33: =IFERROR(365/E27,0) -> 259.56062 | F33: =IFERROR(365/F27,0) -> 194.46818 | G33: =IFERROR(365/G27,0) -> 219.43346 | H33: =IFERROR(365/H27,0) -> 266.86242 | I33: =IFERROR(365/I27,0) -> 210.15979 | J33: =IFERROR(365/J27,0) -> 182.56164 | ... L33: =IFERROR(365/L27,0) -> 277.57317 | N33: =IFERROR(AVERAGE(C33:L33),0) -> 236.0836 | O33: =IFERROR(MEDIAN(C33:L33),0) -> 239.64285
B34: Inventory Days | C34: =IFERROR(365/C28,0) -> 62.246692 | D34: =IFERROR(365/D28,0) -> 58.782299 | E34: =IFERROR(365/E28,0) -> 56.817293 | F34: =IFERROR(365/F28,0) -> 43.389336 | G34: =IFERROR(365/G28,0) -> 45.207884 | H34: =IFERROR(365/H28,0) -> 63.928442 | I34: =IFERROR(365/I28,0) -> 56.629479 | J34: =IFERROR(365/J28,0) -> 58.310307 | ... L34: =IFERROR(365/L28,0) -> 55.371336 | N34: =IFERROR(AVERAGE(C34:L34),0) -> 56.270588 | O34: =IFERROR(MEDIAN(C34:L34),0) -> 57.5638
B35: Cash Conversion Cycle | C35: =C32+C34-C33 -> -163.06314 | D35: =D32+D34-D33 -> -202.32946 | E35: =E32+E34-E33 -> -186.34824 | F35: =F32+F34-F33 -> -131.75494 | G35: =G32+G34-G33 -> -162.20163 | H35: =H32+H34-H33 -> -188.05084 | I35: =I32+I34-I33 -> -141.10922 | J35: =J32+J34-J33 -> -112.40335 | ... L35: =L32+L34-L33 -> -206.23398 | N35: =IFERROR(AVERAGE(C35:L35),0) -> -166.66285 | O35: =IFERROR(MEDIAN(C35:L35),0) -> -168.0984
B37: CFO/Sales | C37: =IFERROR('HISTORICAL FS'!C77/'HISTORICAL FS'!C4,0) -> 0.1686202 | D37: =IFERROR('HISTORICAL FS'!D77/'HISTORICAL FS'!D4,0) -> 0.21389092 | E37: =IFERROR('HISTORICAL FS'!E77/'HISTORICAL FS'!E4,0) -> 0.2302756 | F37: =IFERROR('HISTORICAL FS'!F77/'HISTORICAL FS'!F4,0) -> 0.023866122 | G37: =IFERROR('HISTORICAL FS'!G77/'HISTORICAL FS'!G4,0) -> 0.18903464 | H37: =IFERROR('HISTORICAL FS'!H77/'HISTORICAL FS'!H4,0) -> -0.049323729 | I37: =IFERROR('HISTORICAL FS'!I77/'HISTORICAL FS'!I4,0) -> 0.16033299 | J37: =IFERROR('HISTORICAL FS'!J77/'HISTORICAL FS'!J4,0) -> 0.10885262 | ... L37: =IFERROR('HISTORICAL FS'!L77/'HISTORICAL FS'!L4,0) -> 0.21024387 | N37: =IFERROR(AVERAGE(C37:L37),0) -> 0.14394934 | O37: =IFERROR(MEDIAN(C37:L37),0) -> 0.17616019
B38: CFO/Total Assets | C38: =IFERROR('HISTORICAL FS'!C77/'HISTORICAL FS'!C64,0) -> 0.076733272 | D38: =IFERROR('HISTORICAL FS'!D77/'HISTORICAL FS'!D64,0) -> 0.091981913 | E38: =IFERROR('HISTORICAL FS'!E77/'HISTORICAL FS'!E64,0) -> 0.11093306 | F38: =IFERROR('HISTORICAL FS'!F77/'HISTORICAL FS'!F64,0) -> 0.013596223 | G38: =IFERROR('HISTORICAL FS'!G77/'HISTORICAL FS'!G64,0) -> 0.096983272 | H38: =IFERROR('HISTORICAL FS'!H77/'HISTORICAL FS'!H64,0) -> -0.017423384 | I38: =IFERROR('HISTORICAL FS'!I77/'HISTORICAL FS'!I64,0) -> 0.074320943 | J38: =IFERROR('HISTORICAL FS'!J77/'HISTORICAL FS'!J64,0) -> 0.059405361 | ... L38: =IFERROR('HISTORICAL FS'!L77/'HISTORICAL FS'!L64,0) -> 0.103824 | N38: =IFERROR(AVERAGE(C38:L38),0) -> 0.070445693 | O38: =IFERROR(MEDIAN(C38:L38),0) -> 0.084357593
B39: CFO/Total Debt | C39: =IFERROR('HISTORICAL FS'!C77/'HISTORICAL FS'!C49,0) -> 0.2360539 | D39: =IFERROR('HISTORICAL FS'!D77/'HISTORICAL FS'!D49,0) -> 0.29894471 | E39: =IFERROR('HISTORICAL FS'!E77/'HISTORICAL FS'!E49,0) -> 0.37523296 | F39: =IFERROR('HISTORICAL FS'!F77/'HISTORICAL FS'!F49,0) -> 0.044079892 | G39: =IFERROR('HISTORICAL FS'!G77/'HISTORICAL FS'!G49,0) -> 0.31760777 | H39: =IFERROR('HISTORICAL FS'!H77/'HISTORICAL FS'!H49,0) -> -0.082448506 | I39: =IFERROR('HISTORICAL FS'!I77/'HISTORICAL FS'!I49,0) -> 0.34897762 | J39: =IFERROR('HISTORICAL FS'!J77/'HISTORICAL FS'!J49,0) -> 0.21121453 | ... L39: =IFERROR('HISTORICAL FS'!L77/'HISTORICAL FS'!L49,0) -> 0.54079607 | N39: =IFERROR(AVERAGE(C39:L39),0) -> 0.27613602 | O39: =IFERROR(MEDIAN(C39:L39),0) -> 0.30827624
B41: RETURN ON ASSETS
B42: PAT vs Total Assets | C42: =IFERROR('HISTORICAL FS'!C31/'HISTORICAL FS'!C64,0) -> 0.029464254 | D42: =IFERROR('HISTORICAL FS'!D31/'HISTORICAL FS'!D64,0) -> 0.029160925 | E42: =IFERROR('HISTORICAL FS'!E31/'HISTORICAL FS'!E64,0) -> 0.032308483 | F42: =IFERROR('HISTORICAL FS'!F31/'HISTORICAL FS'!F64,0) -> 0.031505668 | G42: =IFERROR('HISTORICAL FS'!G31/'HISTORICAL FS'!G64,0) -> 0.026921407 | H42: =IFERROR('HISTORICAL FS'!H31/'HISTORICAL FS'!H64,0) -> 0.023716256 | I42: =IFERROR('HISTORICAL FS'!I31/'HISTORICAL FS'!I64,0) -> 0.032192908 | J42: =IFERROR('HISTORICAL FS'!J31/'HISTORICAL FS'!J64,0) -> 0.038650411 | ... L42: =IFERROR('HISTORICAL FS'!L31/'HISTORICAL FS'!L64,0) -> 0.032293471 | N42: =IFERROR(AVERAGE(C42:L42),0) -> 0.031201964 | O42: =IFERROR(MEDIAN(C42:L42),0) -> 0.031849288
B43: EBIT vs Total Assets | C43: =IFERROR(('HISTORICAL FS'!C16-'HISTORICAL FS'!C22)/'HISTORICAL FS'!C64,0) -> 0.050444326 | D43: =IFERROR(('HISTORICAL FS'!D16-'HISTORICAL FS'!D22)/'HISTORICAL FS'!D64,0) -> 0.049039193 | E43: =IFERROR(('HISTORICAL FS'!E16-'HISTORICAL FS'!E22)/'HISTORICAL FS'!E64,0) -> 0.058684315 | F43: =IFERROR(('HISTORICAL FS'!F16-'HISTORICAL FS'!F22)/'HISTORICAL FS'!F64,0) -> 0.063466415 | G43: =IFERROR(('HISTORICAL FS'!G16-'HISTORICAL FS'!G22)/'HISTORICAL FS'!G64,0) -> 0.057663057 | H43: =IFERROR(('HISTORICAL FS'!H16-'HISTORICAL FS'!H22)/'HISTORICAL FS'!H64,0) -> 0.04107222 | I43: =IFERROR(('HISTORICAL FS'!I16-'HISTORICAL FS'!I22)/'HISTORICAL FS'!I64,0) -> 0.052580971 | J43: =IFERROR(('HISTORICAL FS'!J16-'HISTORICAL FS'!J22)/'HISTORICAL FS'!J64,0) -> 0.063525838 | ... L43: =IFERROR(('HISTORICAL FS'!L16-'HISTORICAL FS'!L22)/'HISTORICAL FS'!L64,0) -> 0.05768131 | N43: =IFERROR(AVERAGE(C43:L43),0) -> 0.055778326 | O43: =IFERROR(MEDIAN(C43:L43),0) -> 0.057672183
B44: PAT after Tax benefit vs Total Assets | C44: =(('HISTORICAL FS'!C16-'HISTORICAL FS'!C22)-('HISTORICAL FS'!C19-('HISTORICAL FS'!C19*'HISTORICAL FS'!C29)))/'HISTORICAL FS'!C64 -> 0.046344324 | D44: =(('HISTORICAL FS'!D16-'HISTORICAL FS'!D22)-('HISTORICAL FS'!D19-('HISTORICAL FS'!D19*'HISTORICAL FS'!D29)))/'HISTORICAL FS'!D64 -> 0.045396444 | E44: =(('HISTORICAL FS'!E16-'HISTORICAL FS'!E22)-('HISTORICAL FS'!E19-('HISTORICAL FS'!E19*'HISTORICAL FS'!E29)))/'HISTORICAL FS'!E64 -> 0.052107782 | F44: =(('HISTORICAL FS'!F16-'HISTORICAL FS'!F22)-('HISTORICAL FS'!F19-('HISTORICAL FS'!F19*'HISTORICAL FS'!F29)))/'HISTORICAL FS'!F64 -> 0.052366994 | G44: =(('HISTORICAL FS'!G16-'HISTORICAL FS'!G22)-('HISTORICAL FS'!G19-('HISTORICAL FS'!G19*'HISTORICAL FS'!G29)))/'HISTORICAL FS'!G64 -> 0.044495861 | H44: =(('HISTORICAL FS'!H16-'HISTORICAL FS'!H22)-('HISTORICAL FS'!H19-('HISTORICAL FS'!H19*'HISTORICAL FS'!H29)))/'HISTORICAL FS'!H64 -> 0.025857598 | I44: =(('HISTORICAL FS'!I16-'HISTORICAL FS'!I22)-('HISTORICAL FS'!I19-('HISTORICAL FS'!I19*'HISTORICAL FS'!I29)))/'HISTORICAL FS'!I64 -> 0.045269574 | J44: =(('HISTORICAL FS'!J16-'HISTORICAL FS'!J22)-('HISTORICAL FS'!J19-('HISTORICAL FS'!J19*'HISTORICAL FS'!J29)))/'HISTORICAL FS'!J64 -> 0.054350796 | ... L44: =(('HISTORICAL FS'!L16-'HISTORICAL FS'!L22)-('HISTORICAL FS'!L19-('HISTORICAL FS'!L19*'HISTORICAL FS'!L29)))/'HISTORICAL FS'!L64 -> 0.048794774 | N44: =IFERROR(AVERAGE(C44:L44),0) -> 0.046926161 | O44: =IFERROR(MEDIAN(C44:L44),0) -> 0.047569549
B46: RETURN ON EQUITY
B47: EPS | C47: =IFERROR('HISTORICAL FS'!C36,0) -> 12.765265 | D47: =IFERROR('HISTORICAL FS'!D36,0) -> 14.857773 | E47: =IFERROR('HISTORICAL FS'!E36,0) -> 19.395585 | F47: =IFERROR('HISTORICAL FS'!F36,0) -> 23.243311 | G47: =IFERROR('HISTORICAL FS'!G36,0) -> 23.151948 | H47: =IFERROR('HISTORICAL FS'!H36,0) -> 24.692205 | I47: =IFERROR('HISTORICAL FS'!I36,0) -> 35.658325 | J47: =IFERROR('HISTORICAL FS'!J36,0) -> 45.870285 | ... L47: =IFERROR('HISTORICAL FS'!L36,0) -> 46.527593 | N47: =IFERROR(AVERAGE(C47:L47),0) -> 29.260316 | O47: =IFERROR(MEDIAN(C47:L47),0) -> 23.967758
B48: Cash Flor Earning Per Share | C48: =IFERROR(('HISTORICAL FS'!C31+'HISTORICAL FS'!C22)/'HISTORICAL FS'!C34,0) -> 21.130061 | D48: =IFERROR(('HISTORICAL FS'!D31+'HISTORICAL FS'!D22)/'HISTORICAL FS'!D34,0) -> 23.252981 | E48: =IFERROR(('HISTORICAL FS'!E31+'HISTORICAL FS'!E22)/'HISTORICAL FS'!E34,0) -> 31.757672 | F48: =IFERROR(('HISTORICAL FS'!F31+'HISTORICAL FS'!F22)/'HISTORICAL FS'!F34,0) -> 38.724062 | G48: =IFERROR(('HISTORICAL FS'!G31+'HISTORICAL FS'!G22)/'HISTORICAL FS'!G34,0) -> 39.569792 | H48: =IFERROR(('HISTORICAL FS'!H31+'HISTORICAL FS'!H22)/'HISTORICAL FS'!H34,0) -> 45.649859 | I48: =IFERROR(('HISTORICAL FS'!I31+'HISTORICAL FS'!I22)/'HISTORICAL FS'!I34,0) -> 57.670476 | J48: =IFERROR(('HISTORICAL FS'!J31+'HISTORICAL FS'!J22)/'HISTORICAL FS'!J34,0) -> 75.655522 | ... L48: =IFERROR(('HISTORICAL FS'!L31+'HISTORICAL FS'!L22)/'HISTORICAL FS'!L34,0) -> 85.793355 | N48: =IFERROR(AVERAGE(C48:L48),0) -> 50.321061 | O48: =IFERROR(MEDIAN(C48:L48),0) -> 42.609826
B49: Dividened Per Share | C49: ='HISTORICAL FS'!C39 -> 2.2388578 | D49: ='HISTORICAL FS'!D39 -> 2.3463474 | E49: ='HISTORICAL FS'!E39 -> 2.6292928 | F49: ='HISTORICAL FS'!F39 -> 2.8484907 | G49: ='HISTORICAL FS'!G39 -> 3.0467624 | H49: ='HISTORICAL FS'!H39 -> 3.558274 | I49: ='HISTORICAL FS'!I39 -> 4.0000591 | J49: ='HISTORICAL FS'!J39 -> 4.5002661 | ... L49: ='HISTORICAL FS'!L39 -> 5.4998374 | N49: =IFERROR(AVERAGE(C49:L49),0) -> 3.5668409 | O49: =IFERROR(MEDIAN(C49:L49),0) -> 3.3025182
B50: Dividend Pay Out Ratio | C50: ='HISTORICAL FS'!C41 -> 0.17538671 | D50: ='HISTORICAL FS'!D41 -> 0.15792053 | E50: ='HISTORICAL FS'!E41 -> 0.13556141 | F50: ='HISTORICAL FS'!F41 -> 0.12255098 | G50: ='HISTORICAL FS'!G41 -> 0.13159853 | H50: ='HISTORICAL FS'!H41 -> 0.14410515 | I50: ='HISTORICAL FS'!I41 -> 0.11217743 | J50: ='HISTORICAL FS'!J41 -> 0.098108526 | ... L50: ='HISTORICAL FS'!L41 -> 0.11820593 | N50: =IFERROR(AVERAGE(C50:L50),0) -> 0.13032838 | O50: =IFERROR(MEDIAN(C50:L50),0) -> 0.12707476
B51: Dividend Yield Ratio | C51: =IFERROR(C49/'Data Sheet'!B8,0) -> 0.001541064 | D51: =IFERROR(D49/'Data Sheet'!C8,0) -> 0 | E51: =IFERROR(E49/'Data Sheet'!D8,0) -> 0 | F51: =IFERROR(F49/'Data Sheet'!E8,0) -> 0 | G51: =IFERROR(G49/'Data Sheet'!F8,0) -> 0 | H51: =IFERROR(H49/'Data Sheet'!G8,0) -> 0 | I51: =IFERROR(I49/'Data Sheet'!H8,0) -> 0 | J51: =IFERROR(J49/'Data Sheet'!I8,0) -> 0 | ... L51: =IFERROR(L49/'Data Sheet'!K8,0) -> 0 | N51: =IFERROR(AVERAGE(C51:L51),0) -> 0.0001541064 | O51: =IFERROR(MEDIAN(C51:L51),0) -> 0

Sheet Forcasting
B2: ='Data Sheet'!B1&"-"&'Data Sheet'!A17 -> RELIANCE INDUSTRIES LTD-Sales | G2: ='Data Sheet'!$B$1&"-"&'HISTORICAL FS'!B16&"Forecasting" -> RELIANCE INDUSTRIES LTD-EBIDAForecasting | L2: ='Data Sheet'!$B$1&"-"&'HISTORICAL FS'!B36&"-"&"Forecasting" -> RELIANCE INDUSTRIES LTD-EPS-Forecasting
B3: Year Weight | C3: Year | D3: Salas | E3: Salas Growth | G3: Year Weight | H3: Year | I3: Salas | J3: Salas Growth | L3: Year Weight | M3: Year | N3: Salas | O3: Salas Growth
B4: 1 | C4: 2016 | D4: {=TRANSPOSE('Data Sheet'!B17:K17)} -> 272583 | E4: - | G4: 1 | H4: 2016 | I4: {=TRANSPOSE('HISTORICAL FS'!C16:L16)} -> 41781 | J4: - | L4: 1 | M4: 2016 | N4: {=TRANSPOSE('HISTORICAL FS'!C36:L36)} -> 12.765265 | O4: -
B5: 2 | C5: 2017 | D5: 303954 | E5: =D5/D4-1 -> 0.11508788 | G5: 2 | H5: 2017 | I5: 46307 | J5: =I5/I4-1 -> 0.10832675 | L5: 2 | M5: 2017 | N5: 14.857773 | O5: =N5/N4-1 -> 0.16392203
B6: 3 | C6: 2018 | D6: 390823 | E6: =D6/D5-1 -> 0.28579654 | G6: 3 | H6: 2018 | I6: 64315 | J6: =I6/I5-1 -> 0.38888289 | L6: 3 | M6: 2018 | N6: 19.395585 | O6: =N6/N5-1 -> 0.30541671
B7: 4 | C7: 2019 | D7: 568337 | E7: =D7/D6-1 -> 0.45420561 | G7: 4 | H7: 2019 | I7: 84250 | J7: =I7/I6-1 -> 0.3099588 | L7: 4 | M7: 2019 | N7: 23.243311 | O7: =N7/N6-1 -> 0.19838153
B8: 5 | C8: 2020 | D8: 596679 | E8: =D8/D7-1 -> 0.0498683 | G8: 5 | H8: 2020 | I8: 89266 | J8: =I8/I7-1 -> 0.059537092 | L8: 5 | M8: 2020 | N8: 23.151948 | O8: =N8/N7-1 -> -0.0039307281
B9: 6 | C9: 2021 | D9: 466307 | E9: =D9/D8-1 -> -0.21849604 | G9: 6 | H9: 2021 | I9: 80790 | J9: =I9/I8-1 -> -0.094952165 | L9: 6 | M9: 2021 | N9: 24.692205 | O9: =N9/N8-1 -> 0.066528186
B10: 7 | C10: 2022 | D10: 694673 | E10: =D10/D9-1 -> 0.48973316 | G10: 7 | H10: 2022 | I10: 108581 | J10: =I10/I9-1 -> 0.34399059 | L10: 7 | M10: 2022 | N10: 35.658325 | O10: =N10/N9-1 -> 0.4441126
B11: 8 | C11: 2023 | D11: 876396 | E11: =D11/D10-1 -> 0.26159502 | G11: 8 | H11: 2023 | I11: 142318 | J11: =I11/I10-1 -> 0.31070813 | L11: 8 | M11: 2023 | N11: 45.870285 | O11: =N11/N10-1 -> 0.28638363
B12: 9 | C12: 2024 | D12: 899041 | E12: =D12/D11-1 -> 0.025838776 | G12: 9 | H12: 2024 | I12: 162498 | J12: =I12/I11-1 -> 0.14179513 | L12: 9 | M12: 2024 | N12: 46.440871 | O12: =N12/N11-1 -> 0.012439118
B13: 10 | C13: 2025 | D13: 962820 | E13: =D13/D12-1 -> 0.070941147 | G13: 10 | H13: 2025 | I13: 165598 | J13: =I13/I12-1 -> 0.019077158 | L13: 10 | M13: 2025 | N13: 46.527593 | O13: =N13/N12-1 -> 0.0018673675
B14: 11 | C14: 2026 | D14: =FORECAST(B14,$D$4:$D$13,$B$4:$B$13) -> 1038302.7 | E14: =D14/D13-1 -> 0.078397554 | G14: 11 | H14: 2026 | I14: =FORECAST(G14,$I$4:$I$13,$G$4:$G$13) -> 177977.8 | J14: =I14/I13-1 -> 0.074758149 | L14: 11 | M14: 2026 | N14: =FORECAST(L14,$N$4:$N$13,$L$4:$L$13) -> 52.463697 | O14: =N14/N13-1 -> 0.12758245
B15: 12 | C15: 2027 | D15: =FORECAST(B15,$D$4:$D$13,$B$4:$B$13) -> 1117419.4 | E15: =D15/D14-1 -> 0.076198031 | G15: 12 | H15: 2027 | I15: =FORECAST(G15,$I$4:$I$13,$G$4:$G$13) -> 192415.51 | J15: =I15/I14-1 -> 0.081120843 | L15: 12 | M15: 2027 | N15: =FORECAST(L15,$N$4:$N$13,$L$4:$L$13) -> 56.682494 | O15: =N15/N14-1 -> 0.080413634
B16: 13 | C16: 2028 | D16: =FORECAST(B16,$D$4:$D$13,$B$4:$B$13) -> 1196536 | E16: =D16/D15-1 -> 0.070802983 | G16: 13 | H16: 2028 | I16: =FORECAST(G16,$I$4:$I$13,$G$4:$G$13) -> 206853.22 | J16: =I16/I15-1 -> 0.07503402 | L16: 13 | M16: 2028 | N16: =FORECAST(L16,$N$4:$N$13,$L$4:$L$13) -> 60.90129 | O16: =N16/N15-1 -> 0.074428563
B17: 14 | C17: 2029 | D17: =FORECAST(B17,$D$4:$D$13,$B$4:$B$13) -> 1275652.6 | E17: =D17/D16-1 -> 0.066121392 | G17: 14 | H17: 2029 | I17: =FORECAST(G17,$I$4:$I$13,$G$4:$G$13) -> 221290.93 | J17: =I17/I16-1 -> 0.069796879 | L17: 14 | M17: 2029 | N17: =FORECAST(L17,$N$4:$N$13,$L$4:$L$13) -> 65.120087 | O17: =N17/N16-1 -> 0.069272696
B18: 15 | C18: 2030 | D18: =FORECAST(B18,$D$4:$D$13,$B$4:$B$13) -> 1354769.2 | E18: =D18/D17-1 -> 0.062020509 | G18: 15 | H18: 2030 | I18: =FORECAST(G18,$I$4:$I$13,$G$4:$G$13) -> 235728.64 | J18: =I18/I17-1 -> 0.065243114 | L18: 15 | M18: 2030 | N18: =FORECAST(L18,$N$4:$N$13,$L$4:$L$13) -> 69.338883 | O18: =N18/N17-1 -> 0.064784873
B19: 16 | C19: 2031 | D19: =FORECAST(B19,$D$4:$D$13,$B$4:$B$13) -> 1433885.9 | E19: =D19/D18-1 -> 0.058398598 | G19: 16 | H19: 2031 | I19: =FORECAST(G19,$I$4:$I$13,$G$4:$G$13) -> 250166.35 | J19: =I19/I18-1 -> 0.061247158 | L19: 16 | M19: 2031 | N19: =FORECAST(L19,$N$4:$N$13,$L$4:$L$13) -> 73.55768 | O19: =N19/N18-1 -> 0.060843157

Sheet CFS
C3: 41699 | D3: 42064 | E3: 42430 | F3: 42795 | G3: 43160 | H3: 43525 | I3: 43891 | J3: 44256 | K3: 44621 | L3: 44986 | M3: 45352 | N3: 45717
B4: Cash from Operating Activity - | C4: 43261 | D4: 34374 | E4: 38134 | F4: 49550 | G4: 71459 | H4: 42346 | I4: 94877 | J4: 26958 | K4: 110654 | L4: 115032 | M4: 158788 | N4: 178703
B5: Profit from operations | C5: 38444 | D5: 38994 | E5: 38887 | F5: 44170 | G5: 62765 | H5: 83319 | I5: 85347 | J5: 80129 | K5: 113726 | L5: 140963 | M5: 164383 | N5: 166904
B6: Receivables | C6: -1913 | D6: 1097 | E6: -6880 | F6: -8511 | G6: -21991 | H6: -40136 | I6: -13792 | J6: 959 | K6: -14180 | L6: 13194 | M6: -15674 | N6: -17837
B7: Inventory | C7: -1396 | D7: 3472 | E7: 6758 | F7: -6899 | G7: -10474 | H7: -6724 | I7: -6342 | J7: -7769 | K7: -24983 | L7: -32228 | M7: -12756 | N7: 3134
B8: Payables | C8: 14339 | D8: -2754 | E8: 7951 | F8: 30873 | G8: 51003 | H8: 18078 | I8: 38050 | J8: -43148 | K8: 39888 | L8: -600 | M8: 34796 | N8: 38427
B9: Working capital changes | C9: 11030 | D9: 1815 | E9: 7829 | F9: 15463 | G9: 18538 | H9: -28782 | I9: 17916 | J9: -49958 | K9: 725 | L9: -19634 | M9: 6366 | N9: 23724
B10: Direct taxes | C10: -6213 | D10: -6435 | E10: -8582 | F10: -10083 | G10: -9844 | H10: -12191 | I10: -8386 | J10: -3213 | K10: -3797 | L10: -6297 | M10: -11961 | N10: -11925
B11: Cash from Investing Activity - | C11: -73070 | D11: -64706 | E11: -36186 | F11: -66201 | G11: -68192 | H11: -94507 | I11: -72497 | J11: -142385 | K11: -109162 | L11: -93001 | M11: -113581 | N11: -137535
B12: Fixed assets purchased | C12: -60087 | D12: -63364 | E12: -46898 | F12: -78109 | G12: -73953 | H12: -93626 | I12: -76517 | J12: -105837 | K12: -100145 | L12: -140988 | M12: -152883 | N12: -139967
B13: Fixed assets sold | C13: 148 | D13: 402 | E13: 344 | F13: 1482 | G13: 999 | H13: 849 | I13: 964 | J13: 2319 | K13: 3137 | L13: 9186 | M13: 15307 | N13: 2343
B14: Investments purchased | C14: -765659 | D14: -678241 | E14: -715334 | F14: -654760 | G14: -533984 | H14: -1107439 | I14: -1156843 | J14: -689866 | K14: -667878 | L14: -471822 | M14: -513660 | N14: -684340
B15: Investments sold | C15: 749849 | D15: 666383 | E15: 721182 | F15: 663990 | G15: 537504 | H15: 1103615 | I15: 1174796 | J15: 642551 | K15: 668137 | L15: 501266 | M15: 531355 | N15: 672558
... B28: Net Cash Flow | C28: -16096 | D28: -21888 | E28: -1262 | F28: -8034 | G28: 1266 | H28: 3745 | I28: 19839 | J28: -13523 | K28: 18781 | L28: 32486 | M28: 28561 | N28: 9277

Sheet wacc
B2: Weighted Average Cost of Capital
B4: All figures are in INR unless otherwise stated
B6: Peer Company
G7: Debt/ | H7: Debt/ | I7: Levered | J7: Unlevered | K7: Unlevered
B8: Name of the Comp | D8: Country | E8: Total Debt | F8: Total Equity | G8: Tax Rate 1 | H8: Equity | I8: Capital | J8: Beta 2 | K8: Beta 3
B9: Avenue Super. | D9: India | E9: ='[2]BETA Comps.'!F3 -> 630.38 | F9: ='[2]BETA Comps.'!E3 -> 279783.37 | G9: 0.3 | H9: =E9/F9 -> 0.0022531003 | I9: =E9/(E9+F9) -> 0.0022480353 | J9: =[2]Sheet2!L6 -> 1.2681188 | K9: =J9/(1+(1-G9)*H9) -> 1.2661219
B10: Trent | D10: India | E10: ='[2]BETA Comps.'!F4 -> 4839.33 | F10: ='[2]BETA Comps.'!E4 -> 140524.04 | G10: 0.3 | H10: =E10/F10 -> 0.034437737 | I10: =E10/(E10+F10) -> 0.033291262 | J10: 1 | K10: =J10/(1+(1-G10)*H10) -> 0.97646102
B11: Vedant Fashions | D11: India | E11: ='[2]BETA Comps.'!F5 -> 365.02 | F11: ='[2]BETA Comps.'!E5 -> 22671.01 | G11: 0.3 | H11: =E11/F11 -> 0.016100738 | I11: =E11/(E11+F11) -> 0.015845612 | J11: 1 | K11: =J11/(1+(1-G11)*H11) -> 0.98885509
B12: Aditya Bir. Fas. | D12: India | E12: ='[2]BETA Comps.'!F6 -> 10174.77 | F12: ='[2]BETA Comps.'!E6 -> 19500.64 | G12: 0.3 | H12: =E12/F12 -> 0.52176595 | I12: =E12/(E12+F12) -> 0.34286873 | J12: 1 | K12: =J12/(1+(1-G12)*H12) -> 0.732474
B13: Redtape | D13: India | E13: ='[2]BETA Comps.'!F7 -> 470.82 | F13: ='[2]BETA Comps.'!E7 -> 8657.28 | G13: 0.3 | H13: =E13/F13 -> 0.054384287 | I13: =E13/(E13+F13) -> 0.05157919 | J13: 1 | K13: =J13/(1+(1-G13)*H13) -> 0.9633271
E16: Averages | F16: =AVERAGE(G9:G13) -> 0.3 | G16: =AVERAGE(H9:H13) -> 0.12578836 | H16: =AVERAGE(I9:I13) -> 0.089166565 | I16: 1 | J16: =I16/(1+(1-F16)*G16) -> 0.91907384
E17: Medaian | F17: =MEDIAN(G9:G13) -> 0.3 | G17: =MEDIAN(H9:H13) -> 0.034437737 | H17: =MEDIAN(I9:I13) -> 0.033291262 | I17: 1 | J17: =I17/(1+(1-F17)*G17) -> 0.97646102
B20: Cost of Debt | G20: Cost of Equity
B22: Pre-Tax Cost of debt | E22: 0.084 | G22: Risk Free Rate | K22: 0.065
B23: Tax Rat | E23: 0.3 | G23: Equity Risk Premium | K23: 0.08
B24: Poat Tax Cost Debt | E24: =E22*(1-E23) -> 0.0588 | G24: Levered Beta 4 | K24: =K33 -> 1.4816735
G25: Cost of Equity | K25: =K22+K23*K24 -> 0.18353388
B28: Capital Structure | G28: Levered Beta
D30: Current | E30: Target | G30: Comes Median Unliverd Beta | K30: =J17 -> 0.97646102
B31: Total Debt | C31: 17440 | D31: =C31/$C$33 -> 0.35087013 | E31: 0.425 | G31: Target Debt/Equity | K31: =E35 -> 0.73913043
B32: Market Capitalization | C32: 32265 | D32: =C32/$C$33 -> 0.64912987 | E32: =E33-E31 -> 0.575 | G32: Tax | K32: =E23 -> 0.3
B33: Total Capital | C33: =C31+C32 -> 49705 | D33: =C33/$C$33 -> 1 | E33: 1 | G33: Levered Beta | K33: =K30*(1+(1-K32)*K31) -> 1.4816735
B35: Debt/Equity | D35: =D31/D32 -> 0.54052379 | E35: =E31/E32 -> 0.73913043 | G35: Weighted Average Cost of Capital
J37: Total Cost | K37: Total Weight
G38: Debt | J38: =E24 -> 0.0588 | K38: =E31 -> 0.425
B39: Notes:- | G39: Equity | J39: =K25 -> 0.18353388 | K39: =E32 -> 0.575
B40: 1. Tax Rate considered as Marginal Tax Rate for the Country | G40: Weight Average Cost of Capital | K40: =SUMPRODUCT(J38:J39,K38:K39) -> 0.13052198
B41: 2. Levered Beta is based on 5 years monthly data
B42: 3.Unlevered Beta = Levered Beta/(1+(1-Tax Rate)*Debt/Equity)
B43: 4.Levered Beta = Unlevered Beta*(1+(1-Tax Rate)*Debt/Equity)

Sheet DCF
B3: Calculation of PV of FCFF | G3: Mar-25A | H3: 46082 | I3: 46448 | J3: 46815 | K3: 47181 | L3: 47547
B5: EBIT | G5: ='Intrisic Growth '!L34 -> 112462 | H5: =G5*(1+$G$21) -> 126254.85 | I5: =H5*(1+H21) -> 126254.85 | J5: =I5*(1+I21) -> 126254.85 | K5: =J5*(1+J21) -> 126254.85 | L5: =K5*(1+K21) -> 126254.85
B7: Tax Rate | G7: ='Intrisic Growth '!L45 -> 0.28607713 | H7: 0.2861 | I7: 0.2861 | J7: 0.2861 | K7: 0.2861 | L7: 0.2861
B9: EBIT(1-T) | G9: =G5*(1-G7) -> 80289.194 | H9: =G9*(1+$G$21) -> 90136.226 | I9: =H9*(1+$G$21) -> 101190.94 | J9: =I9*(1+$G$21) -> 113601.46 | K9: =J9*(1+$G$21) -> 127534.06 | L9: =K9*(1+$G$21) -> 143175.41
B11: Less:- Reinvestment Rate | G11: ='Intrisic Growth '!P50 -> 0.85810062 | H11: =G11*(1+$G$21) -> 0.96334198 | I11: =H11*(1+$G$21) -> 1.0814906 | J11: =I11*(1+$G$21) -> 1.2141295 | K11: =J11*(1+$G$21) -> 1.3630359 | L11: =K11*(1+$G$21) -> 1.5302048
B13: Free Cash Flow to Firm (FCFF) | G13: =G9*(1-G11) -> 11392.987 | H13: =G13*(1+$G$21) -> 12790.274 | I13: =H13*(1+$G$21) -> 14358.932 | J13: =I13*(1+$G$21) -> 16119.976 | K13: =J13*(1+$G$21) -> 18097.003 | L13: =K13*(1+$G$21) -> 20316.502
B15: Mid Year Convention | H15: 0.5 | I15: =H15+1 -> 1.5 | J15: =I15+1 -> 2.5 | K15: =J15+1 -> 3.5 | L15: =K15+1 -> 4.5
B17: Discounting Factor | H17: =1/(1+$G$23)^H15 -> 0.94050367 | I17: =1/(1+$G$23)^I15 -> 0.83191985 | J17: =1/(1+$G$23)^J15 -> 0.73587233 | K17: =1/(1+$G$23)^K15 -> 0.65091378 | L17: =1/(1+$G$23)^L15 -> 0.57576393
B19: PV of FCFF | H19: =H13*H17 -> 12029.3 | I19: =I13*I17 -> 11945.48 | J19: =J13*J17 -> 11862.244 | K19: =K13*K17 -> 11779.589 | L19: =L13*L17 -> 11697.509
B21: Expected Growth | G21: ='Intrisic Growth '!P56 -> 0.12264454
B22: Terminal Growth | G22: 0.059
B23: WACC | G23: =wacc!K40 -> 0.13052198
B26: Calculation of Terminal Value
B27: FCFF(n+1) | E27: =L13*(1+$G$21) -> 22808.21
B28: WACC | E28: =G23 -> 0.13052198
B29: Terminal Growth Rate | E29: 0.0509
B31: Terminal Value | E31: =E27/(E28-E29) -> 286456.2
B34: Calculation of Equity Value Per Share
B35: PV of FCFF | E35: =SUM(H19:L19) -> 59314.122
B36: PV of Terminal Value | E36: =E31*L17 -> 164931.15
B37: Value of Operating Assets | E37: =SUM(E35,E36) -> 224245.27
B39: Add: CASH | E39: ='Data Sheet'!K69 -> 106502
B40: Less:- DEBT | E40: ='RAW FS'!N7 -> 236899
B42: Value of Equity | E42: =E37+E39-E40 -> 93848.271
B43: NO. of Shares | E43: ='Data Sheet'!B6 -> 1353.1557
B44: Euity Value Per Share | E44: =E42/E43 -> 69.355119
B46: Share Price | E46: 1465
B47: Discount/Premium | E47: =E46/E44 -> 21.123171

Sheet RAW FS
B2: Particular | C2: 41699 | D2: 42064 | E2: 42430 | F2: 42795 | G2: 43160 | H2: 43525 | I2: 43891 | J2: 44256 | K2: 44621 | L2: 44986 | M2: 45352 | N2: 45717
B4: Equity Capital | C4: 2940 | D4: 2943 | E4: 2948 | F4: 2959 | G4: 5922 | H4: 5926 | I4: 6339 | J4: 6445 | K4: 6765 | L4: 6766 | M4: 6766 | N4: 13532
B5: Reserves | C5: 195747 | D5: 215556 | E5: 228608 | F5: 260750 | G5: 287584 | H5: 381186 | I5: 442827 | J5: 693727 | K5: 772720 | L5: 709106 | M5: 786715 | N5: 829668
B6: Borrowings - | C6: 138761 | D6: 168251 | E6: 194714 | F6: 217475 | G6: 239843 | H6: 307714 | I6: 355133 | J6: 278962 | K6: 319158 | L6: 451664 | M6: 350719 | N6: 374313
B7: Long term Borrowings | C7: 101019 | D7: 128165 | E7: 154957 | F7: 172285 | G7: 164385 | H7: 226345 | I7: 216470 | J7: 182520 | K7: 224883 | L7: 296023 | M7: 222712 | N7: 236899
B8: Short term Borrowings | C8: 32792 | D8: 27965 | E8: 23545 | F8: 31528 | G8: 37429 | H8: 64436 | I8: 93786 | J8: 88128 | K8: 78606 | L8: 130790 | M8: 101910 | N8: 110631
B9: Lease Liabilities | C9: 0 | D9: 0 | E9: 0 | F9: 0 | G9: 0 | H9: 0 | I9: 0 | J9: 8314 | K9: 15669 | L9: 20426 | M9: 21520 | N9: 22045
B10: Other Borrowings | C10: 4950 | D10: 12121 | E10: 16212 | F10: 13662 | G10: 38029 | H10: 16933 | I10: 44877 | J10: 0 | K10: 0 | L10: 4425 | M10: 4577 | N10: 4738
B11: Other Liabilities
B12: Non controlling int | C12: 959 | D12: 3038 | E12: 3356 | F12: 2917 | G12: 3539 | H12: 8280 | I12: 12181 | J12: 99260 | K12: 109499 | L12: 113009 | M12: 132307 | N12: 166426
B13: Trade Payables | C13: 60860 | D13: 59407 | E13: 60296 | F13: 76595 | G13: 106861 | H13: 108309 | I13: 96799 | J13: 108897 | K13: 159330 | L13: 147172 | M13: 178377 | N13: 186789
B14: Other liability items | C14: 29576 | D14: 55291 | E14: 109075 | F14: 146106 | G14: 167524 | H14: 186215 | I14: 249736 | J14: 132774 | K14: 131150 | L14: 178165 | M14: 300164 | N14: 378985
B15: Total Liabilities | C15: 428843 | D15: 504486 | E15: 598997 | F15: 706802 | G15: 811273 | H15: 997630 | I15: 1163015 | J15: 1320065 | K15: 1498622 | L15: 1605882 | M15: 1755048 | N15: 1949713
B17: Fixed Assrts
B18: Land | C18: 9378 | D18: 9859 | E18: 63734 | F18: 65973 | G18: 66765 | H18: 49371 | I18: 68743 | J18: 68768 | K18: 69855 | L18: 79697 | M18: 87287 | N18: 102088
B19: Building | C19: 13239 | D19: 13967 | E19: 15283 | F19: 18813 | G19: 22194 | H19: 27672 | I19: 34380 | J19: 36781 | K19: 47561 | L19: 69747 | M19: 82062 | N19: 106351
B20: Plant Machinery | C20: 147313 | D20: 158698 | E20: 168888 | F20: 179326 | G20: 325183 | H20: 318853 | I20: 449770 | J20: 471201 | K20: 518865 | L20: 557687 | M20: 579067 | N20: 640511
B21: Ships Vessels | C21: 387 | D21: 397 | E21: 422 | F21: 3484 | G21: 5038 | H21: 417 | I21: 502 | J21: 515 | K21: 508 | L21: 518 | M21: 522 | N21: 527
B22: Equipments | C22: 0 | D22: 0 | E22: 0 | F22: 0 | G22: 0 | H22: 0 | I22: 0 | J22: 0 | K22: 32638 | L22: 45067 | M22: 59936 | N22: 63964
B23: Furniture n fittings | C23: 10035 | D23: 4835 | E23: 6282 | F23: 7848 | G23: 10146 | H23: 21817 | I23: 31211 | J23: 38039 | K23: 24970 | L23: 38161 | M23: 43458 | N23: 47640
B24: Vehicles | C24: 582 | D24: 710 | E24: 777 | F24: 1155 | G24: 1199 | H24: 1240 | I24: 1411 | J24: 2336 | K24: 2530 | L24: 3667 | M24: 3745 | N24: 4178
B25: Intangible Assets | C25: 70668 | D25: 88103 | E25: 68660 | F25: 75351 | G25: 76599 | H25: 86765 | I25: 81462 | J25: 77353 | K25: 65970 | L25: 85032 | M25: 112873 | N25: 160656
B26: Other fixed assets | C26: 9417 | D26: 12297 | E26: 11453 | F26: 9343 | G26: 74160 | H26: 90387 | I26: 76299 | J26: 80819 | K26: 120717 | L26: 138426 | M26: 145632 | N26: 249903
B27: Gross Block | C27: 261019 | D27: 288866 | E27: 335499 | F27: 361293 | G27: 581284 | H27: 596522 | I27: 743778 | J27: 775812 | K27: 883614 | L27: 1018002 | M27: 1114582 | N27: 1375818
B28: Accumulated Depreciation | C28: 119602 | D28: 132408 | E28: 150589 | F28: 162767 | G28: 177399 | H28: 198148 | I28: 211120 | J28: 234554 | K28: 255816 | L28: 293197 | M28: 334597 | N28: 376425
B29: Net Block | C29: =C27-C28 -> 141417 | D29: =D27-D28 -> 156458 | E29: =E27-E28 -> 184910 | F29: =F27-F28 -> 198526 | G29: =G27-G28 -> 403885 | H29: =H27-H28 -> 398374 | I29: =I27-I28 -> 532658 | J29: =J27-J28 -> 541258 | ... N29: =N27-N28 -> 999393
B31: CWIP | C31: 91494 | D31: 166462 | E31: 228697 | F31: 324837 | G31: 187022 | H31: 179463 | I31: 109106 | J31: 125953 | K31: 172506 | L31: 293752 | M31: 338855 | N31: 262358
B32: Investments | C32: 60602 | D32: 76451 | E32: 84015 | F32: 82899 | G32: 82862 | H32: 235635 | I32: 276767 | J32: 364828 | K32: 394264 | L32: 235560 | M32: 225672 | N32: 242381
B35: Other Assets -
B36: Inventories | C36: 56720 | D36: 53248 | E36: 46486 | F36: 48951 | G36: 60837 | H36: 67561 | I36: 73903 | J36: 81672 | K36: 107778 | L36: 140008 | M36: 152770 | N36: 146062
B37: Trade receivables | C37: 9411 | D37: 5315 | E37: 4465 | F37: 8177 | G37: 17555 | H37: 30089 | I37: 19656 | J37: 19014 | K37: 23640 | L37: 28448 | M37: 31628 | N37: 42121
B38: Cash Equivalents | C38: 37984 | D38: 12545 | E38: 11028 | F38: 3023 | G38: 4255 | H38: 11081 | I38: 30920 | J38: 17397 | K38: 36178 | L38: 68664 | M38: 97225 | N38: 106502
B39: Loans n Advances | C39: 0 | D39: 0 | E39: 841 | F39: 996 | G39: 2327 | H39: 545 | I39: 669 | J39: 65 | K39: 130 | L39: 176 | M39: 2517 | N39: 5182
B40: Other asset items | C40: 31215 | D40: 34007 | E40: 38555 | F40: 39393 | G40: 52530 | H40: 74882 | I40: 119336 | J40: 169878 | K40: 136328 | L40: 114469 | M40: 126396 | N40: 145714
B41: Total Assets | C41: 428843 | D41: 504486 | E41: 598997 | F41: 706802 | G41: 811273 | H41: 997630 | I41: 1163015 | J41: 1320065 | K41: 1498622 | L41: 1605882 | M41: 1755048 | N41: 1949713

Sheet BETA Comps.
C3: REGEERESSION BETA
C5: Avenue Supermart Weekely Return | G5: Nifty Return | K5: Beta Drifting
C7: Date | D7: Closing Price | E7: Weekely Return | G7: Closing Price | H7: Weekely Return | K7: Levered Raw Beta | M7: =Q12 -> 1.2681188
C8: 44641 | D8: 4001.3 | G8: 17153 | K8: Beta Weught | M8: 0.75
C9: 44648 | D9: 4082.2 | E9: =D9/D8-1 -> 0.020218404 | G9: 17670.449 | H9: =G9/G8-1 -> 0.030166689
C10: 44655 | D10: 4146.25 | E10: =D10/D9-1 -> 0.015690081 | G10: 17784.35 | H10: =G10/G9-1 -> 0.0064458118 | K10: Market Beta | M10: 1
C11: 44662 | D11: 4090.8999 | E11: =D11/D10-1 -> -0.013349436 | G11: 17475.65 | H11: =G11/G10-1 -> -0.017357914 | K11: Market Beta Weight | M11: 0.25 | P11: Beta 1 | Q11: =SLOPE(E9:E112,H9:H112) -> 1.2681188
C12: 44669 | D12: 4028.8501 | E12: =D12/D11-1 -> -0.015167764 | G12: 17171.949 | H12: =G12/G11-1 -> -0.017378533 | P12: Beta 2 | Q12: =_xlfn.COVARIANCE.S(E9:E112,H9:H112)/_xlfn.VAR.S(H9:H112) -> 1.2681188
C13: 44676 | D13: 3944.25 | E13: =D13/D12-1 -> -0.020998572 | G13: 17102.551 | H13: =G13/G12-1 -> -0.0040413838 | K13: Adjusted Beta | M13: =((M7*M8)+M10*M11) -> 1.2010891
C14: 44683 | D14: 3666.2 | E14: =D14/D13-1 -> -0.070495037 | G14: 16411.25 | H14: =G14/G13-1 -> -0.040420917 | P14: Beta 3 | Q14: SUMMARY OUTPUT
C15: 44690 | D15: 3230.6001 | E15: =D15/D14-1 -> -0.11881508 | G15: 15782.15 | H15: =G15/G14-1 -> -0.038333436
C16: 44697 | D16: 3630.3999 | E16: =D16/D15-1 -> 0.12375404 | G16: 16266.15 | H16: =G16/G15-1 -> 0.030667557 | Q16: Regression Statistics
C17: 44704 | D17: 3613.8501 | E17: =D17/D16-1 -> -0.0045586724 | G17: 16352.45 | H17: =G17/G16-1 -> 0.0053054842 | Q17: Multiple R | R17: 0.54371855
C18: 44711 | D18: 3820.1001 | E18: =D18/D17-1 -> 0.057072096 | G18: 16584.301 | H18: =G18/G17-1 -> 0.014178339 | Q18: R Square | R18: 0.29562986
C19: 44718 | D19: 3755.6499 | E19: =D19/D18-1 -> -0.016871337 | G19: 16201.8 | H19: =G19/G18-1 -> -0.02306404 | Q19: Adjusted R Square | R19: 0.28872427
C20: 44725 | D20: 3460.55 | E20: =D20/D19-1 -> -0.07857491 | G20: 15293.5 | H20: =G20/G19-1 -> -0.056061661 | Q20: Standard Error | R20: 0.033739445
C21: 44732 | D21: 3412 | E21: =D21/D20-1 -> -0.014029576 | G21: 15699.25 | H21: =G21/G20-1 -> 0.026530879 | Q21: Observations | R21: 104
C22: 44739 | D22: 3388.75 | E22: =D22/D21-1 -> -0.0068141852 | G22: 15752.05 | H22: =G22/G21-1 -> 0.0033632056
C23: 44746 | D23: 3941.7 | E23: =D23/D22-1 -> 0.16317225 | G23: 16220.6 | H23: =G23/G22-1 -> 0.029745323 | Q23: ANOVA
C24: 44753 | D24: 3926.8 | E24: =D24/D23-1 -> -0.0037800701 | G24: 16049.2 | H24: =G24/G23-1 -> -0.010566774 | R24: df | S24: SS | T24: MS | U24: F | V24: Significance F
C25: 44760 | D25: 3963.3999 | E25: =D25/D24-1 -> 0.0093205288 | G25: 16719.449 | H25: =G25/G24-1 -> 0.041762145 | Q25: Regression | R25: 1 | S25: 0.048733029 | T25: 0.048733029 | U25: 42.810227 | V25: 2.4524721e-09
C26: 44767 | D26: 4243.8501 | E26: =D26/D25-1 -> 0.070760005 | G26: 17158.25 | H26: =G26/G25-1 -> 0.02624493 | Q26: Residual | R26: 102 | S26: 0.11611172 | T26: 0.0011383502
C27: 44774 | D27: 4232.25 | E27: =D27/D26-1 -> -0.0027333901 | G27: 17397.5 | H27: =G27/G26-1 -> 0.01394373 | Q27: Total | R27: 103 | S27: 0.16484475
C28: 44781 | D28: 4336.7002 | E28: =D28/D27-1 -> 0.02467959 | G28: 17698.15 | H28: =G28/G27-1 -> 0.017281241
C29: 44788 | D29: 4382 | E29: =D29/D28-1 -> 0.010445685 | G29: 17758.449 | H29: =G29/G28-1 -> 0.0034070695 | R29: Coefficients | S29: Standard Error | T29: t Stat | U29: P-value | V29: Lower 95% | W29: Upper 95% | X29: Lower 95.0% | Y29: Upper 95.0%
C30: 44795 | D30: 4409.6499 | E30: =D30/D29-1 -> 0.0063098818 | G30: 17558.9 | H30: =G30/G29-1 -> -0.011236839 | Q30: Intercept | R30: -0.0024496943 | S30: 0.0033456076 | T30: -0.73221209 | U30: 0.46571826 | V30: -0.0090856911 | W30: 0.0041863024 | X30: -0.0090856911 | Y30: 0.0041863024
C31: 44802 | D31: 4576.7998 | E31: =D31/D30-1 -> 0.037905482 | G31: 17539.449 | H31: =G31/G30-1 -> -0.0011077671 | Q31: X Variable 1 | R31: 1.2681188 | S31: 0.19381447 | T31: 6.5429525 | U31: 2.4524721e-09 | V31: 0.88368876 | W31: 1.6525489 | X31: 0.88368876 | Y31: 1.6525489
C32: 44809 | D32: 4386.1001 | E32: =D32/D31-1 -> -0.041666604 | G32: 17833.35 | H32: =G32/G31-1 -> 0.016756535
C33: 44816 | D33: 4327.5498 | E33: =D33/D32-1 -> -0.013349055 | G33: 17530.85 | H33: =G33/G32-1 -> -0.016962601
C34: 44823 | D34: 4367 | E34: =D34/D33-1 -> 0.009116058 | G34: 17327.35 | H34: =G34/G33-1 -> -0.011608108
C35: 44830 | D35: 4386.5498 | E35: =D35/D34-1 -> 0.0044767128 | G35: 17094.35 | H35: =G35/G34-1 -> -0.01344695
C36: 44837 | D36: 4471.4502 | E36: =D36/D35-1 -> 0.019354708 | G36: 17314.65 | H36: =G36/G35-1 -> 0.012887345
C37: 44844 | D37: 4306.1499 | E37: =D37/D36-1 -> -0.036967938 | G37: 17185.699 | H37: =G37/G36-1 -> -0.0074475181
C38: 44851 | D38: 4215.5498 | E38: =D38/D37-1 -> -0.021039699 | G38: 17576.301 | H38: =G38/G37-1 -> 0.02272829
C39: 44858 | D39: 4307.3501 | E39: =D39/D38-1 -> 0.021776588 | G39: 17786.801 | H39: =G39/G38-1 -> 0.011976354
C40: 44865 | D40: 4167.3501 | E40: =D40/D39-1 -> -0.032502582 | G40: 18117.15 | H40: =G40/G39-1 -> 0.018572739
C41: 44872 | D41: 4128.3501 | E41: =D41/D40-1 -> -0.009358465 | G41: 18349.699 | H41: =G41/G40-1 -> 0.012835839
C42: 44879 | D42: 3910.6001 | E42: =D42/D41-1 -> -0.052745042 | G42: 18307.65 | H42: =G42/G41-1 -> -0.0022915268
C43: 44886 | D43: 3904.45 | E43: =D43/D42-1 -> -0.0015726862 | G43: 18512.75 | H43: =G43/G42-1 -> 0.011202945
... C112: 45369 | D112: 4010.55 | E112: =D112/D111-1 -> 0.019951158 | G112: 22055.699 | H112: =G112/G111-1 -> 0.0014688778

Sheet Intrisic Growth 
B2: Calculation of ROC | H2: ='RAW FS'!J2 -> 44256 | I2: ='RAW FS'!K2 -> 44621 | J2: ='RAW FS'!L2 -> 44986 | K2: ='RAW FS'!M2 -> 45352 | L2: ='RAW FS'!N2 -> 45717
B4: Current Assets
B5: ='RAW FS'!B36 -> Inventories | H5: ='RAW FS'!J36 -> 81672 | I5: ='RAW FS'!K36 -> 107778 | J5: ='RAW FS'!L36 -> 140008 | K5: ='RAW FS'!M36 -> 152770 | L5: ='RAW FS'!N36 -> 146062
B6: ='RAW FS'!B37 -> Trade receivables | H6: ='RAW FS'!J37 -> 19014 | I6: ='RAW FS'!K37 -> 23640 | J6: ='RAW FS'!L37 -> 28448 | K6: ='RAW FS'!M37 -> 31628 | L6: ='RAW FS'!N37 -> 42121
B7: ='RAW FS'!B39 -> Loans n Advances | H7: ='RAW FS'!J39 -> 65 | I7: ='RAW FS'!K39 -> 130 | J7: ='RAW FS'!L39 -> 176 | K7: ='RAW FS'!M39 -> 2517 | L7: ='RAW FS'!N39 -> 5182
B8: ='RAW FS'!B40 -> Other asset items | H8: ='RAW FS'!J40 -> 169878 | I8: ='RAW FS'!K40 -> 136328 | J8: ='RAW FS'!L40 -> 114469 | K8: ='RAW FS'!M40 -> 126396 | L8: ='RAW FS'!N40 -> 145714
B9: Total Current Assets | H9: =SUM(H5:H8) -> 270629 | I9: =SUM(I5:I8) -> 267876 | J9: =SUM(J5:J8) -> 283101 | K9: =SUM(K5:K8) -> 313311 | L9: =SUM(L5:L8) -> 339079
B11: Current Liabilities
B12: ='RAW FS'!B13 -> Trade Payables | H12: ='RAW FS'!J13 -> 108897 | I12: ='RAW FS'!K13 -> 159330 | J12: ='RAW FS'!L13 -> 147172 | K12: ='RAW FS'!M13 -> 178377 | L12: ='RAW FS'!N13 -> 186789
B13: ='RAW FS'!B14 -> Other liability items | H13: ='RAW FS'!J14 -> 132774 | I13: ='RAW FS'!K14 -> 131150 | J13: ='RAW FS'!L14 -> 178165 | K13: ='RAW FS'!M14 -> 300164 | L13: ='RAW FS'!N14 -> 378985
B14: Total Current Liabilities | H14: =SUM(H12:H13) -> 241671 | I14: =SUM(I12:I13) -> 290480 | J14: =SUM(J12:J13) -> 325337 | K14: =SUM(K12:K13) -> 478541 | L14: =SUM(L12:L13) -> 565774
B16: Net working Capital | H16: =H9-H14 -> 28958 | I16: =I9-I14 -> -22604 | J16: =J9-J14 -> -42236 | K16: =K9-K14 -> -165230 | L16: =L9-L14 -> -226695
B18: Non Current Assets
B19: ='RAW FS'!B18 -> Land | H19: ='RAW FS'!J18 -> 68768 | I19: ='RAW FS'!K18 -> 69855 | J19: ='RAW FS'!L18 -> 79697 | K19: ='RAW FS'!M18 -> 87287 | L19: ='RAW FS'!N18 -> 102088
B20: ='RAW FS'!B19 -> Building | H20: ='RAW FS'!J19 -> 36781 | I20: ='RAW FS'!K19 -> 47561 | J20: ='RAW FS'!L19 -> 69747 | K20: ='RAW FS'!M19 -> 82062 | L20: ='RAW FS'!N19 -> 106351
B21: ='RAW FS'!B20 -> Plant Machinery | H21: ='RAW FS'!J20 -> 471201 | I21: ='RAW FS'!K20 -> 518865 | J21: ='RAW FS'!L20 -> 557687 | K21: ='RAW FS'!M20 -> 579067 | L21: ='RAW FS'!N20 -> 640511
B22: ='RAW FS'!B21 -> Ships Vessels | H22: ='RAW FS'!J21 -> 515 | I22: ='RAW FS'!K21 -> 508 | J22: ='RAW FS'!L21 -> 518 | K22: ='RAW FS'!M21 -> 522 | L22: ='RAW FS'!N21 -> 527
B23: ='RAW FS'!B22 -> Equipments | H23: ='RAW FS'!J22 -> 0 | I23: ='RAW FS'!K22 -> 32638 | J23: ='RAW FS'!L22 -> 45067 | K23: ='RAW FS'!M22 -> 59936 | L23: ='RAW FS'!N22 -> 63964
B24: ='RAW FS'!B23 -> Furniture n fittings | H24: ='RAW FS'!J23 -> 38039 | I24: ='RAW FS'!K23 -> 24970 | J24: ='RAW FS'!L23 -> 38161 | K24: ='RAW FS'!M23 -> 43458 | L24: ='RAW FS'!N23 -> 47640
B25: ='RAW FS'!B24 -> Vehicles | H25: ='RAW FS'!J24 -> 2336 | I25: ='RAW FS'!K24 -> 2530 | J25: ='RAW FS'!L24 -> 3667 | K25: ='RAW FS'!M24 -> 3745 | L25: ='RAW FS'!N24 -> 4178
B26: ='RAW FS'!B25 -> Intangible Assets | H26: ='RAW FS'!J25 -> 77353 | I26: ='RAW FS'!K25 -> 65970 | J26: ='RAW FS'!L25 -> 85032 | K26: ='RAW FS'!M25 -> 112873 | L26: ='RAW FS'!N25 -> 160656
B27: ='RAW FS'!B26 -> Other fixed assets | H27: ='RAW FS'!J26 -> 80819 | I27: ='RAW FS'!K26 -> 120717 | J27: ='RAW FS'!L26 -> 138426 | K27: ='RAW FS'!M26 -> 145632 | L27: ='RAW FS'!N26 -> 249903
B29: Gross Block | H29: =SUM(H19:H27) -> 775812 | I29: =SUM(I19:I27) -> 883614 | J29: =SUM(J19:J27) -> 1018002 | K29: =SUM(K19:K27) -> 1114582 | L29: =SUM(L19:L27) -> 1375818
B30: ='RAW FS'!B28 -> Accumulated Depreciation | H30: =-'RAW FS'!J28 -> -234554 | I30: =-'RAW FS'!K28 -> -255816 | J30: =-'RAW FS'!L28 -> -293197 | K30: =-'RAW FS'!M28 -> -334597 | L30: =-'RAW FS'!N28 -> -376425
B31: Net Non Current Assets | H31: =SUM(H29:H30) -> 541258 | I31: =SUM(I29:I30) -> 627798 | J31: =SUM(J29:J30) -> 724805 | K31: =SUM(K29:K30) -> 779985 | L31: =SUM(L29:L30) -> 999393
B33: Invested Capital | H33: =H31+H16 -> 570216 | I33: =I31+I16 -> 605194 | J33: =J31+J16 -> 682569 | K33: =K31+K16 -> 614755 | L33: =L31+L16 -> 772698
B34: EBIT | H34: ='HISTORICAL FS'!H16-'HISTORICAL FS'!H22 -> 54218 | I34: ='HISTORICAL FS'!I16-'HISTORICAL FS'!I22 -> 78799 | J34: ='HISTORICAL FS'!J16-'HISTORICAL FS'!J22 -> 102015 | K34: ='HISTORICAL FS'!K16-'HISTORICAL FS'!K22 -> 111666 | L34: ='HISTORICAL FS'!L16-'HISTORICAL FS'!L22 -> 112462
B36: ROIC | H36: =H34/H33 -> 0.095083267 | I36: =I34/I33 -> 0.13020453 | J36: =J34/J33 -> 0.14945742 | K36: =K34/K33 -> 0.18164309 | L36: =L34/L33 -> 0.14554457
B38: Calculation of Reinvestment Rate | H38: ='HISTORICAL FS'!H2 -> 44286 | I38: ='HISTORICAL FS'!I2 -> 44651 | J38: ='HISTORICAL FS'!J2 -> 45016 | K38: ='HISTORICAL FS'!K2 -> 45382 | L38: ='HISTORICAL FS'!L2 -> 45747
B41: Net Capex | H41: =-SUM(CFS!J12:J13) -> 103518 | I41: =-SUM(CFS!K12:K13) -> 97008 | J41: =-SUM(CFS!L12:L13) -> 131802 | K41: =-SUM(CFS!M12:M13) -> 137576 | L41: =-SUM(CFS!N12:N13) -> 137624
B42: Change in Working Capital | I42: =I16-H16 -> -51562 | J42: =J16-I16 -> -19632 | K42: =K16-J16 -> -122994 | L42: =L16-K16 -> -61465
B44: EBIT | H44: =H34 -> 54218 | I44: =I34 -> 78799 | J44: =J34 -> 102015 | K44: =K34 -> 111666 | L44: =L34 -> 112462
B45: TAX | H45: ='HISTORICAL FS'!H29 -> 0.052136002 | I45: ='HISTORICAL FS'!I29 -> 0.24869579 | J45: ='HISTORICAL FS'!J29 -> 0.24714958 | K45: ='HISTORICAL FS'!K29 -> 0.29031712 | L45: ='HISTORICAL FS'!L29 -> 0.28607713
B46: EBIT(1-TAX) | H46: =H44*(1-H45) -> 51391.29 | I46: =I44*(1-I45) -> 59202.021 | J46: =J44*(1-J45) -> 76802.036 | K46: =K44*(1-K45) -> 79247.449 | L46: =L44*(1-L45) -> 80289.194
B48: Reinvestment | I48: =I41+I42 -> 45446 | J48: =J41+J42 -> 112170 | K48: =K41+K42 -> 14582 | L48: =L41+L42 -> 76159
B50: Reinvestment Rate | I50: =I48/I46 -> 0.76764272 | J50: =J48/J46 -> 1.4605082 | K50: =K48/K46 -> 0.18400592 | L50: =L48/L46 -> 0.94855853 | N50: 4 Year Median | P50: =MEDIAN(I50:L50) -> 0.85810062
B52: Calculation of ROC | H52: =H2 -> 44256 | I52: =I2 -> 44621 | J52: =J2 -> 44986 | K52: =K2 -> 45352 | L52: =L2 -> 45717
B53: Reinvestment Rate | I53: =I50 -> 0.76764272 | J53: =J50 -> 1.4605082 | K53: =K50 -> 0.18400592 | L53: =L50 -> 0.94855853
B54: ROIC | I54: =H36 -> 0.095083267 | J54: =I36 -> 0.13020453 | K54: =J36 -> 0.14945742 | L54: =K36 -> 0.18164309
B56: Intrisic Growth | I56: =I54*I53 -> 0.072989977 | J56: =J54*J53 -> 0.19016478 | K56: =K54*K53 -> 0.02750105 | L56: =L54*L53 -> 0.17229911 | N56: 4 Year Median | P56: =MEDIAN(I56:L56) -> 0.12264454

Sheet Profit & Loss
A1: ='Data Sheet'!B1 -> RELIANCE INDUSTRIES LTD | H1: =UPDATE | M1: SCREENER.IN
A3: Narration | B3: ='Data Sheet'!B16 -> 42460 | C3: ='Data Sheet'!C16 -> 42825 | D3: ='Data Sheet'!D16 -> 43190 | E3: ='Data Sheet'!E16 -> 43555 | F3: ='Data Sheet'!F16 -> 43921 | G3: ='Data Sheet'!G16 -> 44286 | H3: ='Data Sheet'!H16 -> 44651 | I3: ='Data Sheet'!I16 -> 45016 | ... K3: ='Data Sheet'!K16 -> 45747 | L3: Trailing | M3: Best Case | N3: Worst Case
A4: Sales | B4: ='Data Sheet'!B17 -> 272583 | C4: ='Data Sheet'!C17 -> 303954 | D4: ='Data Sheet'!D17 -> 390823 | E4: ='Data Sheet'!E17 -> 568337 | F4: ='Data Sheet'!F17 -> 596679 | G4: ='Data Sheet'!G17 -> 466307 | H4: ='Data Sheet'!H17 -> 694673 | I4: ='Data Sheet'!I17 -> 876396 | ... K4: ='Data Sheet'!K17 -> 962820 | L4: =SUM(Quarters!H4:K4) -> 999629 | M4: =$K4+M23*K4 -> 1073494.9 | N4: =$K4+N23*L4 -> 1033734.8
A5: Expenses | B5: =SUM('Data Sheet'!B18,'Data Sheet'!B20:B24, -1*'Data Sheet'!B19) -> 230802 | C5: =SUM('Data Sheet'!C18,'Data Sheet'!C20:C24, -1*'Data Sheet'!C19) -> 257647 | D5: =SUM('Data Sheet'!D18,'Data Sheet'!D20:D24, -1*'Data Sheet'!D19) -> 326508 | E5: =SUM('Data Sheet'!E18,'Data Sheet'!E20:E24, -1*'Data Sheet'!E19) -> 484087 | F5: =SUM('Data Sheet'!F18,'Data Sheet'!F20:F24, -1*'Data Sheet'!F19) -> 507413 | G5: =SUM('Data Sheet'!G18,'Data Sheet'!G20:G24, -1*'Data Sheet'!G19) -> 385517 | H5: =SUM('Data Sheet'!H18,'Data Sheet'!H20:H24, -1*'Data Sheet'!H19) -> 586092 | I5: =SUM('Data Sheet'!I18,'Data Sheet'!I20:I24, -1*'Data Sheet'!I19) -> 734078 | ... K5: =SUM('Data Sheet'!K18,'Data Sheet'!K20:K24, -1*'Data Sheet'!K19) -> 797222 | L5: =SUM(Quarters!H5:K5) -> 823218 | M5: =M4-M6 -> 884048.33 | N5: =N4-N6 -> 864798.83
A6: Operating Profit | B6: =B4-B5 -> 41781 | C6: =C4-C5 -> 46307 | D6: =D4-D5 -> 64315 | E6: =E4-E5 -> 84250 | F6: =F4-F5 -> 89266 | G6: =G4-G5 -> 80790 | H6: =H4-H5 -> 108581 | I6: =I4-I5 -> 142318 | ... K6: =K4-K5 -> 165598 | L6: =SUM(Quarters!H6:K6) -> 176411 | M6: =M4*M24 -> 189446.6 | N6: =N4*N24 -> 168936
A7: Other Income | B7: ='Data Sheet'!B25 -> 12212 | C7: ='Data Sheet'!C25 -> 9222 | D7: ='Data Sheet'!D25 -> 9869 | E7: ='Data Sheet'!E25 -> 8406 | F7: ='Data Sheet'!F25 -> 8570 | G7: ='Data Sheet'!G25 -> 22432 | H7: ='Data Sheet'!H25 -> 19600 | I7: ='Data Sheet'!I25 -> 12020 | ... K7: ='Data Sheet'!K25 -> 17824 | L7: =SUM(Quarters!H7:K7) -> 28720 | M7: 0 | N7: 0
A8: Depreciation | B8: ='Data Sheet'!B26 -> 11565 | C8: ='Data Sheet'!C26 -> 11646 | D8: ='Data Sheet'!D26 -> 16706 | E8: ='Data Sheet'!E26 -> 20934 | F8: ='Data Sheet'!F26 -> 22203 | G8: ='Data Sheet'!G26 -> 26572 | H8: ='Data Sheet'!H26 -> 29782 | I8: ='Data Sheet'!I26 -> 40303 | ... K8: ='Data Sheet'!K26 -> 53136 | L8: =SUM(Quarters!H8:K8) -> 54918 | M8: =+$L8 -> 54918 | N8: =+$L8 -> 54918
A9: Interest | B9: ='Data Sheet'!B27 -> 3691 | C9: ='Data Sheet'!C27 -> 3849 | D9: ='Data Sheet'!D27 -> 8052 | E9: ='Data Sheet'!E27 -> 16495 | F9: ='Data Sheet'!F27 -> 22027 | G9: ='Data Sheet'!G27 -> 21189 | H9: ='Data Sheet'!H27 -> 14584 | I9: ='Data Sheet'!I27 -> 19571 | ... K9: ='Data Sheet'!K27 -> 24269 | L9: =SUM(Quarters!H9:K9) -> 26197 | M9: =+$L9 -> 26197 | N9: =+$L9 -> 26197
A10: Profit before tax | B10: ='Data Sheet'!B28 -> 38737 | C10: ='Data Sheet'!C28 -> 40034 | D10: ='Data Sheet'!D28 -> 49426 | E10: ='Data Sheet'!E28 -> 55227 | F10: ='Data Sheet'!F28 -> 53606 | G10: ='Data Sheet'!G28 -> 55461 | H10: ='Data Sheet'!H28 -> 83815 | I10: ='Data Sheet'!I28 -> 94464 | ... K10: ='Data Sheet'!K28 -> 106017 | L10: =SUM(Quarters!H10:K10) -> 124016 | M10: =M6+M7-SUM(M8:M9) -> 108331.6 | N10: =N6+N7-SUM(N8:N9) -> 87820.997
A11: Tax | B11: ='Data Sheet'!B29 -> 8876 | C11: ='Data Sheet'!C29 -> 10201 | D11: ='Data Sheet'!D29 -> 13346 | E11: ='Data Sheet'!E29 -> 15390 | F11: ='Data Sheet'!F29 -> 13726 | G11: ='Data Sheet'!G29 -> 1722 | H11: ='Data Sheet'!H29 -> 15970 | I11: ='Data Sheet'!I29 -> 20376 | ... K11: ='Data Sheet'!K29 -> 25230 | L11: =SUM(Quarters!H11:K11) -> 26951 | M11: =IF($L10>0,$L11/$L10,0) -> 0.21731873 | N11: =IF($L10>0,$L11/$L10,0) -> 0.21731873
A12: Net profit | B12: ='Data Sheet'!B30 -> 29745 | C12: ='Data Sheet'!C30 -> 29901 | D12: ='Data Sheet'!D30 -> 36075 | E12: ='Data Sheet'!E30 -> 39588 | F12: ='Data Sheet'!F30 -> 39354 | G12: ='Data Sheet'!G30 -> 49128 | H12: ='Data Sheet'!H30 -> 60705 | I12: ='Data Sheet'!I30 -> 66702 | ... K12: ='Data Sheet'!K30 -> 69648 | L12: =SUM(Quarters!H12:K12) -> 83106 | M12: =M10-M11*M10 -> 84789.113 | N12: =N10-N11*N10 -> 68735.849
A13: EPS | B13: =IF('Data Sheet'!B93>0,B12/'Data Sheet'!B93,0) -> 21.514126 | C13: =IF('Data Sheet'!C93>0,C12/'Data Sheet'!C93,0) -> 21.55462 | D13: =IF('Data Sheet'!D93>0,D12/'Data Sheet'!D93,0) -> 26.694737 | E13: =IF('Data Sheet'!E93>0,E12/'Data Sheet'!E93,0) -> 29.275435 | F13: =IF('Data Sheet'!F93>0,F12/'Data Sheet'!F93,0) -> 29.100024 | G13: =IF('Data Sheet'!G93>0,G12/'Data Sheet'!G93,0) -> 38.747841 | H13: =IF('Data Sheet'!H93>0,H12/'Data Sheet'!H93,0) -> 44.867626 | I13: =IF('Data Sheet'!I93>0,I12/'Data Sheet'!I93,0) -> 49.294963 | ... K13: =IF('Data Sheet'!K93>0,K12/'Data Sheet'!K93,0) -> 51.467589 | L13: =IF('Data Sheet'!$B6>0,'Profit & Loss'!L12/'Data Sheet'!$B6,0) -> 61.416438 | M13: =IF('Data Sheet'!$B6>0,'Profit & Loss'!M12/'Data Sheet'!$B6,0) -> 62.66028 | N13: =IF('Data Sheet'!$B6>0,'Profit & Loss'!N12/'Data Sheet'!$B6,0) -> 50.796705
A14: Price to earning | B14: =IF(B15>0,B15/B13,"") -> 11.037399 | C14: =IF(C15>0,C15/C13,"") -> 13.922305 | D14: =IF(D15>0,D15/D13,"") -> 15.024685 | E14: =IF(E15>0,E15/E13,"") -> 21.158695 | F14: =IF(F15>0,F15/F13,"") -> 17.390363 | G14: =IF(G15>0,G15/G13,"") -> 23.711773 | H14: =IF(H15>0,H15/H13,"") -> 26.935011 | I14: =IF(I15>0,I15/I13,"") -> 21.690046 | ... K14: =IF(K15>0,K15/K13,"") -> 24.774815 | L14: =IF(L13>0,L15/L13,0) -> 23.654905 | M14: =M25 -> 24.749613 | N14: =N25 -> 20.743517
A15: Price | B15: ='Data Sheet'!B90 -> 237.46 | C15: ='Data Sheet'!C90 -> 300.09 | D15: ='Data Sheet'!D90 -> 401.08 | E15: ='Data Sheet'!E90 -> 619.43 | F15: ='Data Sheet'!F90 -> 506.06 | G15: ='Data Sheet'!G90 -> 918.78 | H15: ='Data Sheet'!H90 -> 1208.51 | I15: ='Data Sheet'!I90 -> 1069.21 | ... K15: ='Data Sheet'!K90 -> 1275.1 | L15: ='Data Sheet'!B8 -> 1452.8 | M15: =M13*M14 -> 1550.8177 | N15: =N13*N14 -> 1053.7023
A17: RATIOS:
A18: Dividend Payout | B18: =IF('Data Sheet'!B30>0, 'Data Sheet'!B31/'Data Sheet'!B30, 0) -> 0.10406455 | C18: =IF('Data Sheet'!C30>0, 'Data Sheet'!C31/'Data Sheet'!C30, 0) -> 0.10885589 | D18: =IF('Data Sheet'!D30>0, 'Data Sheet'!D31/'Data Sheet'!D30, 0) -> 0.098494802 | E18: =IF('Data Sheet'!E30>0, 'Data Sheet'!E31/'Data Sheet'!E30, 0) -> 0.097299687 | F18: =IF('Data Sheet'!F30>0, 'Data Sheet'!F31/'Data Sheet'!F30, 0) -> 0.10469965 | G18: =IF('Data Sheet'!G30>0, 'Data Sheet'!G31/'Data Sheet'!G30, 0) -> 0.091831542 | H18: =IF('Data Sheet'!H30>0, 'Data Sheet'!H31/'Data Sheet'!H30, 0) -> 0.089152459 | I18: =IF('Data Sheet'!I30>0, 'Data Sheet'!I31/'Data Sheet'!I30, 0) -> 0.091292615 | ... K18: =IF('Data Sheet'!K30>0, 'Data Sheet'!K31/'Data Sheet'!K30, 0) -> 0.10686021
A19: OPM | B19: =IF(B6>0,B6/B4,0) -> 0.15327808 | C19: =IF(C6>0,C6/C4,0) -> 0.15234871 | D19: =IF(D6>0,D6/D4,0) -> 0.16456299 | E19: =IF(E6>0,E6/E4,0) -> 0.14823951 | F19: =IF(F6>0,F6/F4,0) -> 0.14960473 | G19: =IF(G6>0,G6/G4,0) -> 0.17325496 | H19: =IF(H6>0,H6/H4,0) -> 0.1563052 | I19: =IF(I6>0,I6/I4,0) -> 0.16239006 | ... L19: =IF(L6>0,L6/L4,0) -> 0.17647647
G22: TRENDS: | H22: 10 YEARS | I22: 7 YEARS | J22: 5 YEARS | K22: 3 YEARS | L22: RECENT | M22: BEST | N22: WORST
G23: Sales Growth | H23: =IF(B4=0,"",POWER($K4/B4,1/9)-1) -> 0.15051964 | I23: =IF(D4=0,"",POWER($K4/D4,1/7)-1) -> 0.13746451 | J23: =IF(F4=0,"",POWER($K4/F4,1/5)-1) -> 0.10042607 | K23: =IF(H4=0,"",POWER($K4/H4, 1/3)-1) -> 0.11494872 | L23: =IF(ISERROR(MAX(IF(J4=0,"",(K4-J4)/J4),IF(K4=0,"",(L4-K4)/K4))),"",MAX(IF(J4=0,"",(K4-J4)/J4),IF(K4=0,"",(L4-K4)/K4))) -> 0.070941147 | M23: =MAX(K23:L23) -> 0.11494872 | N23: =MIN(H23:L23) -> 0.070941147
G24: OPM | H24: =IF(SUM(B4:$K$4)=0,"",SUMPRODUCT(B19:$K$19,B4:$K$4)/SUM(B4:$K$4)) -> 0.16342295 | I24: =IF(SUM(E4:$K$4)=0,"",SUMPRODUCT(E19:$K$19,E4:$K$4)/SUM(E4:$K$4)) -> 0.16454569 | J24: =IF(SUM(G4:$K$4)=0,"",SUMPRODUCT(G19:$K$19,G4:$K$4)/SUM(G4:$K$4)) -> 0.16920875 | K24: =IF(SUM(I4:$K$4)=0, "", SUMPRODUCT(I19:$K$19,I4:$K$4)/SUM(I4:$K$4)) -> 0.17179322 | L24: =L19 -> 0.17647647 | M24: =MAX(K24:L24) -> 0.17647647 | N24: =MIN(H24:L24) -> 0.16342295
G25: Price to Earning | H25: =IF(ISERROR(AVERAGEIF(B14:$L14,">0")),"",AVERAGEIF(B14:$L14,">0")) -> 20.743517 | I25: =IF(ISERROR(AVERAGEIF(E14:$L14,">0")),"",AVERAGEIF(E14:$L14,">0")) -> 23.524287 | J25: =IF(ISERROR(AVERAGEIF(G14:$L14,">0")),"",AVERAGEIF(G14:$L14,">0")) -> 24.940873 | K25: =IF(ISERROR(AVERAGEIF(I14:$L14,">0")),"",AVERAGEIF(I14:$L14,">0")) -> 24.749613 | L25: =L14 -> 23.654905 | M25: =MAX(K25:L25) -> 24.749613 | N25: =MIN(H25:L25) -> 20.743517

Sheet Quarters
A1: ='Profit & Loss'!A1 -> RELIANCE INDUSTRIES LTD | E1: =UPDATE | J1: SCREENER.IN
A3: Narration | B3: ='Data Sheet'!B41 -> 45107 | C3: ='Data Sheet'!C41 -> 45199 | D3: ='Data Sheet'!D41 -> 45291 | E3: ='Data Sheet'!E41 -> 45382 | F3: ='Data Sheet'!F41 -> 45473 | G3: ='Data Sheet'!G41 -> 45565 | H3: ='Data Sheet'!H41 -> 45657 | I3: ='Data Sheet'!I41 -> 45747 | ... K3: ='Data Sheet'!K41 -> 45930
A4: Sales | B4: ='Data Sheet'!B42 -> 207559 | C4: ='Data Sheet'!C42 -> 231886 | D4: ='Data Sheet'!D42 -> 225086 | E4: ='Data Sheet'!E42 -> 236533 | F4: ='Data Sheet'!F42 -> 231784 | G4: ='Data Sheet'!G42 -> 231535 | H4: ='Data Sheet'!H42 -> 239986 | I4: ='Data Sheet'!I42 -> 261388 | ... K4: ='Data Sheet'!K42 -> 254623
A5: Expenses | B5: ='Data Sheet'!B43 -> 169466 | C5: ='Data Sheet'!C43 -> 190918 | D5: ='Data Sheet'!D43 -> 184430 | E5: ='Data Sheet'!E43 -> 194017 | F5: ='Data Sheet'!F43 -> 193019 | G5: ='Data Sheet'!G43 -> 192477 | H5: ='Data Sheet'!H43 -> 196197 | I5: ='Data Sheet'!I43 -> 217556 | ... K5: ='Data Sheet'!K43 -> 208738
A6: Operating Profit | B6: ='Data Sheet'!B50 -> 38093 | C6: ='Data Sheet'!C50 -> 40968 | D6: ='Data Sheet'!D50 -> 40656 | E6: ='Data Sheet'!E50 -> 42516 | F6: ='Data Sheet'!F50 -> 38765 | G6: ='Data Sheet'!G50 -> 39058 | H6: ='Data Sheet'!H50 -> 43789 | I6: ='Data Sheet'!I50 -> 43832 | ... K6: ='Data Sheet'!K50 -> 45885
A7: Other Income | B7: ='Data Sheet'!B44 -> 3813 | C7: ='Data Sheet'!C44 -> 3841 | D7: ='Data Sheet'!D44 -> 3869 | E7: ='Data Sheet'!E44 -> 4534 | F7: ='Data Sheet'!F44 -> 3983 | G7: ='Data Sheet'!G44 -> 4876 | H7: ='Data Sheet'!H44 -> 4214 | I7: ='Data Sheet'!I44 -> 4905 | ... K7: ='Data Sheet'!K44 -> 4482
A8: Depreciation | B8: ='Data Sheet'!B45 -> 11775 | C8: ='Data Sheet'!C45 -> 12585 | D8: ='Data Sheet'!D45 -> 12903 | E8: ='Data Sheet'!E45 -> 13569 | F8: ='Data Sheet'!F45 -> 13596 | G8: ='Data Sheet'!G45 -> 12880 | H8: ='Data Sheet'!H45 -> 13181 | I8: ='Data Sheet'!I45 -> 13479 | ... K8: ='Data Sheet'!K45 -> 14416
A9: Interest | B9: ='Data Sheet'!B46 -> 5837 | C9: ='Data Sheet'!C46 -> 5731 | D9: ='Data Sheet'!D46 -> 5789 | E9: ='Data Sheet'!E46 -> 5761 | F9: ='Data Sheet'!F46 -> 5918 | G9: ='Data Sheet'!G46 -> 6017 | H9: ='Data Sheet'!H46 -> 6179 | I9: ='Data Sheet'!I46 -> 6155 | ... K9: ='Data Sheet'!K46 -> 6827
A10: Profit before tax | B10: ='Data Sheet'!B47 -> 24294 | C10: ='Data Sheet'!C47 -> 26493 | D10: ='Data Sheet'!D47 -> 25833 | E10: ='Data Sheet'!E47 -> 27720 | F10: ='Data Sheet'!F47 -> 23234 | G10: ='Data Sheet'!G47 -> 25037 | H10: ='Data Sheet'!H47 -> 28643 | I10: ='Data Sheet'!I47 -> 29103 | ... K10: ='Data Sheet'!K47 -> 29124
A11: Tax | B11: ='Data Sheet'!B48 -> 6112 | C11: ='Data Sheet'!C48 -> 6673 | D11: ='Data Sheet'!D48 -> 6345 | E11: ='Data Sheet'!E48 -> 6577 | F11: ='Data Sheet'!F48 -> 5786 | G11: ='Data Sheet'!G48 -> 5936 | H11: ='Data Sheet'!H48 -> 6839 | I11: ='Data Sheet'!I48 -> 6669 | ... K11: ='Data Sheet'!K48 -> 6978
A12: Net profit | B12: ='Data Sheet'!B49 -> 16011 | C12: ='Data Sheet'!C49 -> 17394 | D12: ='Data Sheet'!D49 -> 17265 | E12: ='Data Sheet'!E49 -> 18951 | F12: ='Data Sheet'!F49 -> 15138 | G12: ='Data Sheet'!G49 -> 16563 | H12: ='Data Sheet'!H49 -> 18540 | I12: ='Data Sheet'!I49 -> 19407 | ... K12: ='Data Sheet'!K49 -> 18165
A14: OPM | B14: =IF(B4>0,B6/B4,"") -> 0.18352854 | C14: =IF(C4>0,C6/C4,"") -> 0.17667302 | D14: =IF(D4>0,D6/D4,"") -> 0.18062429 | E14: =IF(E4>0,E6/E4,"") -> 0.17974659 | F14: =IF(F4>0,F6/F4,"") -> 0.16724623 | G14: =IF(G4>0,G6/G4,"") -> 0.16869156 | H14: =IF(H4>0,H6/H4,"") -> 0.18246481 | I14: =IF(I4>0,I6/I4,"") -> 0.16768941 | ... K14: =IF(K4>0,K6/K4,"") -> 0.1802076

Sheet Balance Sheet
A1: ='Profit & Loss'!A1 -> RELIANCE INDUSTRIES LTD | E1: =UPDATE | J1: SCREENER.IN
A3: Narration | B3: ='Data Sheet'!B56 -> 42460 | C3: ='Data Sheet'!C56 -> 42825 | D3: ='Data Sheet'!D56 -> 43190 | E3: ='Data Sheet'!E56 -> 43555 | F3: ='Data Sheet'!F56 -> 43921 | G3: ='Data Sheet'!G56 -> 44286 | H3: ='Data Sheet'!H56 -> 44651 | I3: ='Data Sheet'!I56 -> 45016 | ... K3: ='Data Sheet'!K56 -> 45747
A4: Equity Share Capital | B4: ='Data Sheet'!B57 -> 2948 | C4: ='Data Sheet'!C57 -> 2959 | D4: ='Data Sheet'!D57 -> 5922 | E4: ='Data Sheet'!E57 -> 5926 | F4: ='Data Sheet'!F57 -> 6339 | G4: ='Data Sheet'!G57 -> 6445 | H4: ='Data Sheet'!H57 -> 6765 | I4: ='Data Sheet'!I57 -> 6766 | ... K4: ='Data Sheet'!K57 -> 13532
A5: Reserves | B5: ='Data Sheet'!B58 -> 228608 | C5: ='Data Sheet'!C58 -> 260750 | D5: ='Data Sheet'!D58 -> 287584 | E5: ='Data Sheet'!E58 -> 381186 | F5: ='Data Sheet'!F58 -> 442827 | G5: ='Data Sheet'!G58 -> 693727 | H5: ='Data Sheet'!H58 -> 772720 | I5: ='Data Sheet'!I58 -> 709106 | ... K5: ='Data Sheet'!K58 -> 829668
A6: Borrowings | B6: ='Data Sheet'!B59 -> 194714 | C6: ='Data Sheet'!C59 -> 217475 | D6: ='Data Sheet'!D59 -> 239843 | E6: ='Data Sheet'!E59 -> 307714 | F6: ='Data Sheet'!F59 -> 355133 | G6: ='Data Sheet'!G59 -> 278962 | H6: ='Data Sheet'!H59 -> 319158 | I6: ='Data Sheet'!I59 -> 451664 | ... K6: ='Data Sheet'!K59 -> 374313
A7: Other Liabilities | B7: ='Data Sheet'!B60 -> 172727 | C7: ='Data Sheet'!C60 -> 225618 | D7: ='Data Sheet'!D60 -> 277924 | E7: ='Data Sheet'!E60 -> 302804 | F7: ='Data Sheet'!F60 -> 358716 | G7: ='Data Sheet'!G60 -> 340931 | H7: ='Data Sheet'!H60 -> 399979 | I7: ='Data Sheet'!I60 -> 438346 | ... K7: ='Data Sheet'!K60 -> 732200
A8: Total | B8: ='Data Sheet'!B61 -> 598997 | C8: ='Data Sheet'!C61 -> 706802 | D8: ='Data Sheet'!D61 -> 811273 | E8: ='Data Sheet'!E61 -> 997630 | F8: ='Data Sheet'!F61 -> 1163015 | G8: ='Data Sheet'!G61 -> 1320065 | H8: ='Data Sheet'!H61 -> 1498622 | I8: ='Data Sheet'!I61 -> 1605882 | ... K8: ='Data Sheet'!K61 -> 1949713
A10: Net Block | B10: ='Data Sheet'!B62 -> 184910 | C10: ='Data Sheet'!C62 -> 198526 | D10: ='Data Sheet'!D62 -> 403885 | E10: ='Data Sheet'!E62 -> 398374 | F10: ='Data Sheet'!F62 -> 532658 | G10: ='Data Sheet'!G62 -> 541258 | H10: ='Data Sheet'!H62 -> 627798 | I10: ='Data Sheet'!I62 -> 724805 | ... K10: ='Data Sheet'!K62 -> 999393
A11: Capital Work in Progress | B11: ='Data Sheet'!B63 -> 228697 | C11: ='Data Sheet'!C63 -> 324837 | D11: ='Data Sheet'!D63 -> 187022 | E11: ='Data Sheet'!E63 -> 179463 | F11: ='Data Sheet'!F63 -> 109106 | G11: ='Data Sheet'!G63 -> 125953 | H11: ='Data Sheet'!H63 -> 172506 | I11: ='Data Sheet'!I63 -> 293752 | ... K11: ='Data Sheet'!K63 -> 262358
A12: Investments | B12: ='Data Sheet'!B64 -> 84015 | C12: ='Data Sheet'!C64 -> 82899 | D12: ='Data Sheet'!D64 -> 82862 | E12: ='Data Sheet'!E64 -> 235635 | F12: ='Data Sheet'!F64 -> 276767 | G12: ='Data Sheet'!G64 -> 364828 | H12: ='Data Sheet'!H64 -> 394264 | I12: ='Data Sheet'!I64 -> 235560 | ... K12: ='Data Sheet'!K64 -> 242381
A13: Other Assets | B13: ='Data Sheet'!B65 -> 101375 | C13: ='Data Sheet'!C65 -> 100540 | D13: ='Data Sheet'!D65 -> 137504 | E13: ='Data Sheet'!E65 -> 184158 | F13: ='Data Sheet'!F65 -> 244484 | G13: ='Data Sheet'!G65 -> 288026 | H13: ='Data Sheet'!H65 -> 304054 | I13: ='Data Sheet'!I65 -> 351765 | ... K13: ='Data Sheet'!K65 -> 445581
A14: Total | B14: ='Data Sheet'!B66 -> 598997 | C14: ='Data Sheet'!C66 -> 706802 | D14: ='Data Sheet'!D66 -> 811273 | E14: ='Data Sheet'!E66 -> 997630 | F14: ='Data Sheet'!F66 -> 1163015 | G14: ='Data Sheet'!G66 -> 1320065 | H14: ='Data Sheet'!H66 -> 1498622 | I14: ='Data Sheet'!I66 -> 1605882 | ... K14: ='Data Sheet'!K66 -> 1949713
A16: Working Capital | B16: =B13-B7 -> -71352 | C16: =C13-C7 -> -125078 | D16: =D13-D7 -> -140420 | E16: =E13-E7 -> -118646 | F16: =F13-F7 -> -114232 | G16: =G13-G7 -> -52905 | H16: =H13-H7 -> -95925 | I16: =I13-I7 -> -86581 | ... K16: =K13-K7 -> -286619
A17: Debtors | B17: ='Data Sheet'!B67 -> 4465 | C17: ='Data Sheet'!C67 -> 8177 | D17: ='Data Sheet'!D67 -> 17555 | E17: ='Data Sheet'!E67 -> 30089 | F17: ='Data Sheet'!F67 -> 19656 | G17: ='Data Sheet'!G67 -> 19014 | H17: ='Data Sheet'!H67 -> 23640 | I17: ='Data Sheet'!I67 -> 28448 | ... K17: ='Data Sheet'!K67 -> 42121
A18: Inventory | B18: ='Data Sheet'!B68 -> 46486 | C18: ='Data Sheet'!C68 -> 48951 | D18: ='Data Sheet'!D68 -> 60837 | E18: ='Data Sheet'!E68 -> 67561 | F18: ='Data Sheet'!F68 -> 73903 | G18: ='Data Sheet'!G68 -> 81672 | H18: ='Data Sheet'!H68 -> 107778 | I18: ='Data Sheet'!I68 -> 140008 | ... K18: ='Data Sheet'!K68 -> 146062
A20: Debtor Days | B20: =IF('Profit & Loss'!B4>0,'Balance Sheet'!B17/('Profit & Loss'!B4/365),0) -> 5.9788211 | C20: =IF('Profit & Loss'!C4>0,'Balance Sheet'!C17/('Profit & Loss'!C4/365),0) -> 9.8192654 | D20: =IF('Profit & Loss'!D4>0,'Balance Sheet'!D17/('Profit & Loss'!D4/365),0) -> 16.395082 | E20: =IF('Profit & Loss'!E4>0,'Balance Sheet'!E17/('Profit & Loss'!E4/365),0) -> 19.323896 | F20: =IF('Profit & Loss'!F4>0,'Balance Sheet'!F17/('Profit & Loss'!F4/365),0) -> 12.023953 | G20: =IF('Profit & Loss'!G4>0,'Balance Sheet'!G17/('Profit & Loss'!G4/365),0) -> 14.883135 | H20: =IF('Profit & Loss'!H4>0,'Balance Sheet'!H17/('Profit & Loss'!H4/365),0) -> 12.421096 | I20: =IF('Profit & Loss'!I4>0,'Balance Sheet'!I17/('Profit & Loss'!I4/365),0) -> 11.847977 | ... K20: =IF('Profit & Loss'!K4>0,'Balance Sheet'!K17/('Profit & Loss'!K4/365),0) -> 15.96785
A21: Inventory Turnover | B21: =IF('Balance Sheet'!B18>0,'Profit & Loss'!B4/'Balance Sheet'!B18,0) -> 5.8637654 | C21: =IF('Balance Sheet'!C18>0,'Profit & Loss'!C4/'Balance Sheet'!C18,0) -> 6.2093522 | D21: =IF('Balance Sheet'!D18>0,'Profit & Loss'!D4/'Balance Sheet'!D18,0) -> 6.4241005 | E21: =IF('Balance Sheet'!E18>0,'Profit & Loss'!E4/'Balance Sheet'!E18,0) -> 8.4122053 | F21: =IF('Balance Sheet'!F18>0,'Profit & Loss'!F4/'Balance Sheet'!F18,0) -> 8.073813 | G21: =IF('Balance Sheet'!G18>0,'Profit & Loss'!G4/'Balance Sheet'!G18,0) -> 5.7095088 | H21: =IF('Balance Sheet'!H18>0,'Profit & Loss'!H4/'Balance Sheet'!H18,0) -> 6.4454063 | I21: =IF('Balance Sheet'!I18>0,'Profit & Loss'!I4/'Balance Sheet'!I18,0) -> 6.2596137 | ... K21: =IF('Balance Sheet'!K18>0,'Profit & Loss'!K4/'Balance Sheet'!K18,0) -> 6.5918583
A23: Return on Equity | B23: =IF(SUM('Balance Sheet'!B4:B5)>0,'Profit & Loss'!B12/SUM('Balance Sheet'!B4:B5),"") -> 0.12845705 | C23: =IF(SUM('Balance Sheet'!C4:C5)>0,'Profit & Loss'!C12/SUM('Balance Sheet'!C4:C5),"") -> 0.11338635 | D23: =IF(SUM('Balance Sheet'!D4:D5)>0,'Profit & Loss'!D12/SUM('Balance Sheet'!D4:D5),"") -> 0.1229106 | E23: =IF(SUM('Balance Sheet'!E4:E5)>0,'Profit & Loss'!E12/SUM('Balance Sheet'!E4:E5),"") -> 0.10226498 | F23: =IF(SUM('Balance Sheet'!F4:F5)>0,'Profit & Loss'!F12/SUM('Balance Sheet'!F4:F5),"") -> 0.087615714 | G23: =IF(SUM('Balance Sheet'!G4:G5)>0,'Profit & Loss'!G12/SUM('Balance Sheet'!G4:G5),"") -> 0.070165616 | H23: =IF(SUM('Balance Sheet'!H4:H5)>0,'Profit & Loss'!H12/SUM('Balance Sheet'!H4:H5),"") -> 0.077878343 | I23: =IF(SUM('Balance Sheet'!I4:I5)>0,'Profit & Loss'!I12/SUM('Balance Sheet'!I4:I5),"") -> 0.093175875 | ... K23: =IF(SUM('Balance Sheet'!K4:K5)>0,'Profit & Loss'!K12/SUM('Balance Sheet'!K4:K5),"") -> 0.08259962
A24: Return on Capital Emp | C24: =IF((B4+B5+B6+C4+C5+C6)>0,('Profit & Loss'!C10+'Profit & Loss'!C9)*2/(B4+B5+B6+C4+C5+C6),"") -> 0.096716748 | D24: =IF((C4+C5+C6+D4+D5+D6)>0,('Profit & Loss'!D10+'Profit & Loss'!D9)*2/(C4+C5+C6+D4+D5+D6),"") -> 0.11330928 | E24: =IF((D4+D5+D6+E4+E5+E6)>0,('Profit & Loss'!E10+'Profit & Loss'!E9)*2/(D4+D5+D6+E4+E5+E6),"") -> 0.11679443 | F24: =IF((E4+E5+E6+F4+F5+F6)>0,('Profit & Loss'!F10+'Profit & Loss'!F9)*2/(E4+E5+E6+F4+F5+F6),"") -> 0.10090286 | G24: =IF((F4+F5+F6+G4+G5+G6)>0,('Profit & Loss'!G10+'Profit & Loss'!G9)*2/(F4+F5+F6+G4+G5+G6),"") -> 0.085957813 | H24: =IF((G4+G5+G6+H4+H5+H6)>0,('Profit & Loss'!H10+'Profit & Loss'!H9)*2/(G4+G5+G6+H4+H5+H6),"") -> 0.09471565 | I24: =IF((H4+H5+H6+I4+I5+I6)>0,('Profit & Loss'!I10+'Profit & Loss'!I9)*2/(H4+H5+H6+I4+I5+I6),"") -> 0.10064077 | J24: =IF((I4+I5+I6+J4+J5+J6)>0,('Profit & Loss'!J10+'Profit & Loss'!J9)*2/(I4+I5+I6+J4+J5+J6),"") -> 0.11027038 | K24: =IF((J4+J5+J6+K4+K5+K6)>0,('Profit & Loss'!K10+'Profit & Loss'!K9)*2/(J4+J5+J6+K4+K5+K6),"") -> 0.11033178

Sheet Cash Flow
A1: ='Balance Sheet'!A1 -> RELIANCE INDUSTRIES LTD | E1: =UPDATE | J1: SCREENER.IN
A3: Narration | B3: ='Data Sheet'!B81 -> 42460 | C3: ='Data Sheet'!C81 -> 42825 | D3: ='Data Sheet'!D81 -> 43190 | E3: ='Data Sheet'!E81 -> 43555 | F3: ='Data Sheet'!F81 -> 43921 | G3: ='Data Sheet'!G81 -> 44286 | H3: ='Data Sheet'!H81 -> 44651 | I3: ='Data Sheet'!I81 -> 45016 | ... K3: ='Data Sheet'!K81 -> 45747
A4: Cash from Operating Activity | B4: ='Data Sheet'!B82 -> 38134 | C4: ='Data Sheet'!C82 -> 49550 | D4: ='Data Sheet'!D82 -> 71459 | E4: ='Data Sheet'!E82 -> 42346 | F4: ='Data Sheet'!F82 -> 94877 | G4: ='Data Sheet'!G82 -> 26958 | H4: ='Data Sheet'!H82 -> 110654 | I4: ='Data Sheet'!I82 -> 115032 | ... K4: ='Data Sheet'!K82 -> 178703
A5: Cash from Investing Activity | B5: ='Data Sheet'!B83 -> -36186 | C5: ='Data Sheet'!C83 -> -66201 | D5: ='Data Sheet'!D83 -> -68192 | E5: ='Data Sheet'!E83 -> -94507 | F5: ='Data Sheet'!F83 -> -72497 | G5: ='Data Sheet'!G83 -> -142385 | H5: ='Data Sheet'!H83 -> -109162 | I5: ='Data Sheet'!I83 -> -93001 | ... K5: ='Data Sheet'!K83 -> -137535
A6: Cash from Financing Activity | B6: ='Data Sheet'!B84 -> -3210 | C6: ='Data Sheet'!C84 -> 8617 | D6: ='Data Sheet'!D84 -> -2001 | E6: ='Data Sheet'!E84 -> 55906 | F6: ='Data Sheet'!F84 -> -2541 | G6: ='Data Sheet'!G84 -> 101904 | H6: ='Data Sheet'!H84 -> 17289 | I6: ='Data Sheet'!I84 -> 10455 | ... K6: ='Data Sheet'!K84 -> -31891
A7: Net Cash Flow | B7: ='Data Sheet'!B85 -> -1262 | C7: ='Data Sheet'!C85 -> -8034 | D7: ='Data Sheet'!D85 -> 1266 | E7: ='Data Sheet'!E85 -> 3745 | F7: ='Data Sheet'!F85 -> 19839 | G7: ='Data Sheet'!G85 -> -13523 | H7: ='Data Sheet'!H85 -> 18781 | I7: ='Data Sheet'!I85 -> 32486 | ... K7: ='Data Sheet'!K85 -> 9277

Sheet Customization
A1: How to use it?
A3: You can customize this workbook as you want.
B4: You can add custom formating, add conditional formating, add your own formulas… do ANYTHING.
B5: Please don't edit the "Data Sheet" only.
A7: After customization, you can upload this back on Screener.
B8: Upload on: | C8: https://www.screener.in/excel/
A10: Download your customized workbooks now onwards.
B11: Now whenever you will "Export to excel" from Screener, it will export your customized file.
A14: TESTING:
B15: This is a testing feature currently.
B16: You can report any formula errors on the worksheet at: support@screener.in
